<?xml version="1.0" encoding="UTF-8" standalone="yes"?>
<w:document xmlns:wpc="http://schemas.microsoft.com/office/word/2010/wordprocessingCanvas" xmlns:cx="http://schemas.microsoft.com/office/drawing/2014/chartex" xmlns:cx1="http://schemas.microsoft.com/office/drawing/2015/9/8/chartex" xmlns:cx2="http://schemas.microsoft.com/office/drawing/2015/10/21/chartex" xmlns:cx3="http://schemas.microsoft.com/office/drawing/2016/5/9/chartex" xmlns:cx4="http://schemas.microsoft.com/office/drawing/2016/5/10/chartex" xmlns:cx5="http://schemas.microsoft.com/office/drawing/2016/5/11/chartex" xmlns:cx6="http://schemas.microsoft.com/office/drawing/2016/5/12/chartex" xmlns:cx7="http://schemas.microsoft.com/office/drawing/2016/5/13/chartex" xmlns:cx8="http://schemas.microsoft.com/office/drawing/2016/5/14/chartex" xmlns:mc="http://schemas.openxmlformats.org/markup-compatibility/2006" xmlns:aink="http://schemas.microsoft.com/office/drawing/2016/ink" xmlns:am3d="http://schemas.microsoft.com/office/drawing/2017/model3d" xmlns:o="urn:schemas-microsoft-com:office:office" xmlns:oel="http://schemas.microsoft.com/office/2019/extlst" xmlns:r="http://schemas.openxmlformats.org/officeDocument/2006/relationships" xmlns:m="http://schemas.openxmlformats.org/officeDocument/2006/math" xmlns:v="urn:schemas-microsoft-com:vml" xmlns:wp14="http://schemas.microsoft.com/office/word/2010/wordprocessingDrawing" xmlns:wp="http://schemas.openxmlformats.org/drawingml/2006/wordprocessingDrawing" xmlns:w10="urn:schemas-microsoft-com:office:word" xmlns:w="http://schemas.openxmlformats.org/wordprocessingml/2006/main" xmlns:w14="http://schemas.microsoft.com/office/word/2010/wordml" xmlns:w15="http://schemas.microsoft.com/office/word/2012/wordml" xmlns:w16cex="http://schemas.microsoft.com/office/word/2018/wordml/cex" xmlns:w16cid="http://schemas.microsoft.com/office/word/2016/wordml/cid" xmlns:w16="http://schemas.microsoft.com/office/word/2018/wordml" xmlns:w16du="http://schemas.microsoft.com/office/word/2023/wordml/word16du" xmlns:w16sdtdh="http://schemas.microsoft.com/office/word/2020/wordml/sdtdatahash" xmlns:w16sdtfl="http://schemas.microsoft.com/office/word/2024/wordml/sdtformatlock" xmlns:w16se="http://schemas.microsoft.com/office/word/2015/wordml/symex" xmlns:wpg="http://schemas.microsoft.com/office/word/2010/wordprocessingGroup" xmlns:wpi="http://schemas.microsoft.com/office/word/2010/wordprocessingInk" xmlns:wne="http://schemas.microsoft.com/office/word/2006/wordml" xmlns:wps="http://schemas.microsoft.com/office/word/2010/wordprocessingShape" mc:Ignorable="w14 w15 w16se w16cid w16 w16cex w16sdtdh w16sdtfl w16du wp14"><w:body><w:p w14:paraId="67BBA043" w14:textId="6C39318E" w:rsidR="00AD3C9A" w:rsidRPr="00806D19" w:rsidRDefault="00D420DF"><w:pPr><w:pStyle w:val="BodyText"/><w:rPr><w:rFonts w:ascii="Georgia" w:hAnsi="Georgia"/></w:rPr></w:pPr><w:r w:rsidRPr="00806D19"><w:rPr><w:rFonts w:ascii="Georgia" w:hAnsi="Georgia"/><w:b/><w:noProof/><w:sz w:val="24"/></w:rPr><mc:AlternateContent><mc:Choice Requires="wps"><w:drawing><wp:anchor distT="0" distB="0" distL="114300" distR="114300" simplePos="0" relativeHeight="251708928" behindDoc="0" locked="0" layoutInCell="1" allowOverlap="1" wp14:anchorId="2DD3B806" wp14:editId="4B8E59F7"><wp:simplePos x="0" y="0"/><wp:positionH relativeFrom="column"><wp:posOffset>46702</wp:posOffset></wp:positionH><wp:positionV relativeFrom="paragraph"><wp:posOffset>1733550</wp:posOffset></wp:positionV><wp:extent cx="3633849" cy="1127892"/><wp:effectExtent l="0" t="0" r="0" b="0"/><wp:wrapNone/><wp:docPr id="335776933" name="Rectangle 14"/><wp:cNvGraphicFramePr/><a:graphic xmlns:a="http://schemas.openxmlformats.org/drawingml/2006/main"><a:graphicData uri="http://schemas.microsoft.com/office/word/2010/wordprocessingShape"><wps:wsp><wps:cNvSpPr/><wps:spPr><a:xfrm><a:off x="0" y="0"/><a:ext cx="3633849" cy="1127892"/></a:xfrm><a:prstGeom prst="rect"><a:avLst/></a:prstGeom><a:noFill/><a:ln><a:noFill/></a:ln></wps:spPr><wps:style><a:lnRef idx="0"><a:scrgbClr r="0" g="0" b="0"/></a:lnRef><a:fillRef idx="0"><a:scrgbClr r="0" g="0" b="0"/></a:fillRef><a:effectRef idx="0"><a:scrgbClr r="0" g="0" b="0"/></a:effectRef><a:fontRef idx="minor"><a:schemeClr val="dk1"/></a:fontRef></wps:style><wps:bodyPr rot="0" spcFirstLastPara="0" vertOverflow="overflow" horzOverflow="overflow" vert="horz" wrap="square" lIns="91440" tIns="45720" rIns="91440" bIns="45720" numCol="1" spcCol="0" rtlCol="0" fromWordArt="0" anchor="ctr" anchorCtr="0" forceAA="0" compatLnSpc="1"><a:prstTxWarp prst="textNoShape"><a:avLst/></a:prstTxWarp><a:noAutofit/></wps:bodyPr></wps:wsp></a:graphicData></a:graphic><wp14:sizeRelV relativeFrom="margin"><wp14:pctHeight>0</wp14:pctHeight></wp14:sizeRelV></wp:anchor></w:drawing></mc:Choice><mc:Fallback><w:pict><v:rect w14:anchorId="41474826" id="Rectangle 14" o:spid="_x0000_s1026" style="position:absolute;margin-left:3.7pt;margin-top:136.5pt;width:286.15pt;height:88.8pt;z-index:251708928;visibility:visible;mso-wrap-style:square;mso-height-percent:0;mso-wrap-distance-left:9pt;mso-wrap-distance-top:0;mso-wrap-distance-right:9pt;mso-wrap-distance-bottom:0;mso-position-horizontal:absolute;mso-position-horizontal-relative:text;mso-position-vertical:absolute;mso-position-vertical-relative:text;mso-height-percent:0;mso-height-relative:margin;v-text-anchor:middle" o:gfxdata="UEsDBBQABgAIAAAAIQC2gziS/gAAAOEBAAATAAAAW0NvbnRlbnRfVHlwZXNdLnhtbJSRQU7DMBBF&#xA;90jcwfIWJU67QAgl6YK0S0CoHGBkTxKLZGx5TGhvj5O2G0SRWNoz/78nu9wcxkFMGNg6quQqL6RA&#xA;0s5Y6ir5vt9lD1JwBDIwOMJKHpHlpr69KfdHjyxSmriSfYz+USnWPY7AufNIadK6MEJMx9ApD/oD&#xA;OlTrorhX2lFEilmcO2RdNtjC5xDF9pCuTyYBB5bi6bQ4syoJ3g9WQ0ymaiLzg5KdCXlKLjvcW893&#xA;SUOqXwnz5DrgnHtJTxOsQfEKIT7DmDSUCaxw7Rqn8787ZsmRM9e2VmPeBN4uqYvTtW7jvijg9N/y&#xA;JsXecLq0q+WD6m8AAAD//wMAUEsDBBQABgAIAAAAIQA4/SH/1gAAAJQBAAALAAAAX3JlbHMvLnJl&#xA;bHOkkMFqwzAMhu+DvYPRfXGawxijTi+j0GvpHsDYimMaW0Yy2fr2M4PBMnrbUb/Q94l/f/hMi1qR&#xA;JVI2sOt6UJgd+ZiDgffL8ekFlFSbvV0oo4EbChzGx4f9GRdb25HMsYhqlCwG5lrLq9biZkxWOiqY&#xA;22YiTra2kYMu1l1tQD30/bPm3wwYN0x18gb45AdQl1tp5j/sFB2T0FQ7R0nTNEV3j6o9feQzro1i&#xA;OWA14Fm+Q8a1a8+Bvu/d/dMb2JY5uiPbhG/ktn4cqGU/er3pcvwCAAD//wMAUEsDBBQABgAIAAAA&#xA;IQDGCM30WQIAAB0FAAAOAAAAZHJzL2Uyb0RvYy54bWysVEtvGjEQvlfqf7B8L8sSmhDEEqFEVJWi&#xA;BCWpcjZeG1b1etyxYaG/vmPv8mjaS6pedu15zzffeHKzqw3bKvQV2ILnvT5nykooK7sq+LeX+acR&#xA;Zz4IWwoDVhV8rzy/mX78MGncWA1gDaZUyCiI9ePGFXwdghtnmZdrVQvfA6csKTVgLQJdcZWVKBqK&#xA;Xpts0O9fZg1g6RCk8p6kd62ST1N8rZUMj1p7FZgpONUW0hfTdxm/2XQixisUbl3JrgzxD1XUorKU&#xA;9BjqTgTBNlj9EaquJIIHHXoS6gy0rqRKPVA3ef9NN89r4VTqhcDx7giT/39h5cP22S2QYGicH3s6&#xA;xi52Guv4p/rYLoG1P4KldoFJEl5cXlyMhtecSdLl+eBqdD2IcGYnd4c+fFFQs3goONI0Ekhie+9D&#xA;a3owidkszCtj0kSM/U1AMaMkO9WYTmFvVLQz9klpVpWp1CjwElfLW4OsnTRRkWZ/mHcKRg7RUFPC&#xA;d/p2LtFbJYK90//olPKDDUf/urKACaBEfxUb2Aoibvk975DVrf0BihaAiMUSyv2C+oWW4d7JeUWg&#xA;3wsfFgKJ0gQArWl4pI820BQcuhNna8Cff5NHe2IaaTlraEUK7n9sBCrOzFdLHLzOh8O4U+ky/Hw1&#xA;oAuea5bnGrupb4GayelBcDIdo30wh6NGqF9pm2cxK6mElZS74DLg4XIb2oHSeyDVbJbMaI+cCPf2&#xA;2ckYPKIaSfWyexXoOuYFIu0DHNZJjN8QsLWNnhZmmwC6Suw84drhTTuY+N29F3HJz+/J6vSqTX8B&#xA;AAD//wMAUEsDBBQABgAIAAAAIQB0hbPR3QAAAAkBAAAPAAAAZHJzL2Rvd25yZXYueG1sTI/NTsMw&#xA;EITvSLyDtUjcqJ3SNm3IpoKiXrhRkLhuk20c4Z8odtPw9pgTPY5mNPNNuZ2sESMPofMOIZspEOxq&#xA;33SuRfj82D+sQYRIriHjHSP8cIBtdXtTUtH4i3vn8RBbkUpcKAhBx9gXUoZas6Uw8z275J38YCkm&#xA;ObSyGeiSyq2Rc6VW0lLn0oKmnnea6+/D2SJML18kvdF8ImnV27jPXrOdQby/m56fQESe4n8Y/vAT&#xA;OlSJ6ejPrgnCIOSLFESY54/pUvKX+SYHcURYLNUKZFXK6wfVLwAAAP//AwBQSwECLQAUAAYACAAA&#xA;ACEAtoM4kv4AAADhAQAAEwAAAAAAAAAAAAAAAAAAAAAAW0NvbnRlbnRfVHlwZXNdLnhtbFBLAQIt&#xA;ABQABgAIAAAAIQA4/SH/1gAAAJQBAAALAAAAAAAAAAAAAAAAAC8BAABfcmVscy8ucmVsc1BLAQIt&#xA;ABQABgAIAAAAIQDGCM30WQIAAB0FAAAOAAAAAAAAAAAAAAAAAC4CAABkcnMvZTJvRG9jLnhtbFBL&#xA;AQItABQABgAIAAAAIQB0hbPR3QAAAAkBAAAPAAAAAAAAAAAAAAAAALMEAABkcnMvZG93bnJldi54&#xA;bWxQSwUGAAAAAAQABADzAAAAvQUAAAAA&#xA;" filled="f" stroked="f"/></w:pict></mc:Fallback></mc:AlternateContent></w:r><w:r w:rsidR="0080206E" w:rsidRPr="00806D19"><w:rPr><w:rFonts w:ascii="Georgia" w:hAnsi="Georgia"/><w:noProof/></w:rPr><w:drawing><wp:anchor distT="0" distB="0" distL="114300" distR="114300" simplePos="0" relativeHeight="251642368" behindDoc="0" locked="0" layoutInCell="1" allowOverlap="1" wp14:anchorId="1D8A4863" wp14:editId="193B7FC7"><wp:simplePos x="0" y="0"/><wp:positionH relativeFrom="column"><wp:posOffset>-59377</wp:posOffset></wp:positionH><wp:positionV relativeFrom="paragraph"><wp:posOffset>-285338</wp:posOffset></wp:positionV><wp:extent cx="7562850" cy="1569085"/><wp:effectExtent l="0" t="0" r="0" b="0"/><wp:wrapSquare wrapText="bothSides"/><wp:docPr id="1752840558" name="Picture 11"/><wp:cNvGraphicFramePr><a:graphicFrameLocks xmlns:a="http://schemas.openxmlformats.org/drawingml/2006/main" noChangeAspect="1"/></wp:cNvGraphicFramePr><a:graphic xmlns:a="http://schemas.openxmlformats.org/drawingml/2006/main"><a:graphicData uri="http://schemas.openxmlformats.org/drawingml/2006/picture"><pic:pic xmlns:pic="http://schemas.openxmlformats.org/drawingml/2006/picture"><pic:nvPicPr><pic:cNvPr id="0" name="Picture 2"/><pic:cNvPicPr><a:picLocks noChangeAspect="1" noChangeArrowheads="1"/></pic:cNvPicPr></pic:nvPicPr><pic:blipFill><a:blip r:embed="rId5" cstate="print"><a:extLst><a:ext uri="{28A0092B-C50C-407E-A947-70E740481C1C}"><a14:useLocalDpi xmlns:a14="http://schemas.microsoft.com/office/drawing/2010/main" val="0"/></a:ext></a:extLst></a:blip><a:srcRect/><a:stretch><a:fillRect/></a:stretch></pic:blipFill><pic:spPr bwMode="auto"><a:xfrm><a:off x="0" y="0"/><a:ext cx="7562850" cy="1569085"/></a:xfrm><a:prstGeom prst="rect"><a:avLst/></a:prstGeom><a:noFill/><a:ln><a:noFill/></a:ln></pic:spPr></pic:pic></a:graphicData></a:graphic><wp14:sizeRelV relativeFrom="margin"><wp14:pctHeight>0</wp14:pctHeight></wp14:sizeRelV></wp:anchor></w:drawing></w:r></w:p><w:p w14:paraId="3547DCBC" w14:textId="1E8E08E6" w:rsidR="00D420DF" w:rsidRPr="00806D19" w:rsidRDefault="00806D19" w:rsidP="00D420DF"><w:pPr><w:pStyle w:val="BodyText"/><w:spacing w:before="124"/><w:rPr><w:rFonts w:ascii="Georgia" w:hAnsi="Georgia"/><w:sz w:val="24"/></w:rPr></w:pPr><w:r w:rsidRPr="00806D19"><w:rPr><w:rFonts w:ascii="Georgia" w:hAnsi="Georgia"/><w:noProof/><w:sz w:val="24"/></w:rPr><mc:AlternateContent><mc:Choice Requires="wps"><w:drawing><wp:anchor distT="45720" distB="45720" distL="114300" distR="114300" simplePos="0" relativeHeight="251710976" behindDoc="0" locked="0" layoutInCell="1" allowOverlap="1" wp14:anchorId="787FF299" wp14:editId="5A75A66A"><wp:simplePos x="0" y="0"/><wp:positionH relativeFrom="column"><wp:posOffset>427355</wp:posOffset></wp:positionH><wp:positionV relativeFrom="paragraph"><wp:posOffset>88900</wp:posOffset></wp:positionV><wp:extent cx="3858895" cy="1404620"/><wp:effectExtent l="0" t="0" r="0" b="8890"/><wp:wrapSquare wrapText="bothSides"/><wp:docPr id="217" name="Text Box 2"/><wp:cNvGraphicFramePr><a:graphicFrameLocks xmlns:a="http://schemas.openxmlformats.org/drawingml/2006/main"/></wp:cNvGraphicFramePr><a:graphic xmlns:a="http://schemas.openxmlformats.org/drawingml/2006/main"><a:graphicData uri="http://schemas.microsoft.com/office/word/2010/wordprocessingShape"><wps:wsp><wps:cNvSpPr txBox="1"><a:spLocks noChangeArrowheads="1"/></wps:cNvSpPr><wps:spPr bwMode="auto"><a:xfrm><a:off x="0" y="0"/><a:ext cx="3858895" cy="1404620"/></a:xfrm><a:prstGeom prst="rect"><a:avLst/></a:prstGeom><a:noFill/><a:ln><a:noFill/></a:ln></wps:spPr><wps:style><a:lnRef idx="0"><a:scrgbClr r="0" g="0" b="0"/></a:lnRef><a:fillRef idx="0"><a:scrgbClr r="0" g="0" b="0"/></a:fillRef><a:effectRef idx="0"><a:scrgbClr r="0" g="0" b="0"/></a:effectRef><a:fontRef idx="minor"><a:schemeClr val="dk1"/></a:fontRef></wps:style><wps:txbx><w:txbxContent><w:p w14:paraId="7904E301" w14:textId="5B745E1E" w:rsidR="00806D19" w:rsidRPr="00806D19" w:rsidRDefault="00806D19" w:rsidP="00806D19"><w:pPr><w:rPr><w:b/><w:bCs/><w:color w:val="102744"/></w:rPr></w:pPr><w:r w:rsidRPr="00806D19"><w:rPr><w:b/><w:bCs/><w:color w:val="102744"/></w:rPr><w:t>BILL TO:</w:t></w:r></w:p><w:p w14:paraId="4B8587FC" w14:textId="77777777" w:rsidR="00806D19" w:rsidRDefault="00806D19" w:rsidP="00806D19"><w:r w:rsidRPr="00806D19"><w:rPr><w:b/><w:bCs/><w:color w:val="102744"/></w:rPr><w:t>Customer Name:</w:t></w:r><w:r w:rsidRPr="00806D19"><w:rPr><w:color w:val="102744"/></w:rPr><w:t xml:space="preserve"> </w:t></w:r><w:r><w:t>Rushabh Chaudhary</w:t></w:r></w:p><w:p w14:paraId="36CB2F5B" w14:textId="6A313903" w:rsidR="00806D19" w:rsidRDefault="00806D19" w:rsidP="00806D19"><w:r w:rsidRPr="00806D19"><w:rPr><w:b/><w:bCs/></w:rPr><w:t>Customer Email:</w:t></w:r><w:r><w:t xml:space="preserve"> rushab.chaudhary4@gmail.com</w:t></w:r></w:p></w:txbxContent></wps:txbx><wps:bodyPr rot="0" vert="horz" wrap="square" lIns="91440" tIns="45720" rIns="91440" bIns="45720" anchor="t" anchorCtr="0"><a:spAutoFit/></wps:bodyPr></wps:wsp></a:graphicData></a:graphic><wp14:sizeRelH relativeFrom="margin"><wp14:pctWidth>0</wp14:pctWidth></wp14:sizeRelH><wp14:sizeRelV relativeFrom="margin"><wp14:pctHeight>20000</wp14:pctHeight></wp14:sizeRelV></wp:anchor></w:drawing></mc:Choice><mc:Fallback><w:pict><v:shapetype w14:anchorId="787FF299" id="_x0000_t202" coordsize="21600,21600" o:spt="202" path="m,l,21600r21600,l21600,xe"><v:stroke joinstyle="miter"/><v:path gradientshapeok="t" o:connecttype="rect"/></v:shapetype><v:shape id="Text Box 2" o:spid="_x0000_s1026" type="#_x0000_t202" style="position:absolute;margin-left:33.65pt;margin-top:7pt;width:303.85pt;height:110.6pt;z-index:251710976;visibility:visible;mso-wrap-style:square;mso-width-percent:0;mso-height-percent:200;mso-wrap-distance-left:9pt;mso-wrap-distance-top:3.6pt;mso-wrap-distance-right:9pt;mso-wrap-distance-bottom:3.6pt;mso-position-horizontal:absolute;mso-position-horizontal-relative:text;mso-position-vertical:absolute;mso-position-vertical-relative:text;mso-width-percent:0;mso-height-percent:200;mso-width-relative:margin;mso-height-relative:margin;v-text-anchor:top" o:gfxdata="UEsDBBQABgAIAAAAIQC2gziS/gAAAOEBAAATAAAAW0NvbnRlbnRfVHlwZXNdLnhtbJSRQU7DMBBF&#xA;90jcwfIWJU67QAgl6YK0S0CoHGBkTxKLZGx5TGhvj5O2G0SRWNoz/78nu9wcxkFMGNg6quQqL6RA&#xA;0s5Y6ir5vt9lD1JwBDIwOMJKHpHlpr69KfdHjyxSmriSfYz+USnWPY7AufNIadK6MEJMx9ApD/oD&#xA;OlTrorhX2lFEilmcO2RdNtjC5xDF9pCuTyYBB5bi6bQ4syoJ3g9WQ0ymaiLzg5KdCXlKLjvcW893&#xA;SUOqXwnz5DrgnHtJTxOsQfEKIT7DmDSUCaxw7Rqn8787ZsmRM9e2VmPeBN4uqYvTtW7jvijg9N/y&#xA;JsXecLq0q+WD6m8AAAD//wMAUEsDBBQABgAIAAAAIQA4/SH/1gAAAJQBAAALAAAAX3JlbHMvLnJl&#xA;bHOkkMFqwzAMhu+DvYPRfXGawxijTi+j0GvpHsDYimMaW0Yy2fr2M4PBMnrbUb/Q94l/f/hMi1qR&#xA;JVI2sOt6UJgd+ZiDgffL8ekFlFSbvV0oo4EbChzGx4f9GRdb25HMsYhqlCwG5lrLq9biZkxWOiqY&#xA;22YiTra2kYMu1l1tQD30/bPm3wwYN0x18gb45AdQl1tp5j/sFB2T0FQ7R0nTNEV3j6o9feQzro1i&#xA;OWA14Fm+Q8a1a8+Bvu/d/dMb2JY5uiPbhG/ktn4cqGU/er3pcvwCAAD//wMAUEsDBBQABgAIAAAA&#xA;IQALFj4JLwIAAKIEAAAOAAAAZHJzL2Uyb0RvYy54bWysVMtu2zAQvBfoPxC815JdO3UEy0HqwEWB&#xA;9IGm/QCKoiwhFJdd0pbcr8+Skh23PaXohaDI3eHszK5WN32r2UGha8DkfDpJOVNGQtmYXc5/fN++&#xA;WXLmvDCl0GBUzo/K8Zv161erzmZqBjXoUiEjEOOyzua89t5mSeJkrVrhJmCVocsKsBWePnGXlCg6&#xA;Qm91MkvTq6QDLC2CVM7R6d1wydcRv6qU9F+qyinPdM6Jm48rxrUIa7JeiWyHwtaNHGmIf2DRisbQ&#xA;o2eoO+EF22PzF1TbSAQHlZ9IaBOoqkaqWANVM03/qOahFlbFWkgcZ88yuf8HKz8fHuxXZL5/Dz0Z&#xA;GItw9h7ko2MGNrUwO3WLCF2tREkPT4NkSWddNqYGqV3mAkjRfYKSTBZ7DxGor7ANqlCdjNDJgONZ&#xA;dNV7Junw7XKxXF4vOJN0N52n86tZtCUR2SndovMfFLQsbHKO5GqEF4d75wMdkZ1CwmsGto3W0Vlt&#xA;fjugwHAS6QfGI3d/1CrEafNNVawpI9Vw4CTuio1GNnQMtTSVcOqbCEYJIbCiB1+YO6aEbBUb9YX5&#xA;56T4Phh/zm8bAzgYGcZIhQIOggagfBzcI75D/EmKQYDgo++LnpQL2wLKI5mKMAwNDTltasBfnHU0&#xA;MDl3P/cCFWf6o6HGuJ7O52HC4sd88Y5cZHh5U1zeCCMJKuees2G78VHjqLq9pQbaNtHaZyYjWRqE&#xA;6Pg4tGHSLr9j1POvZf0EAAD//wMAUEsDBBQABgAIAAAAIQColiA+3gAAAAkBAAAPAAAAZHJzL2Rv&#xA;d25yZXYueG1sTI9BT8MwDIXvSPyHyEjcWErHWlSaThPaxpExKs5ZY9qKxomarCv/HnOCm+339Py9&#xA;cj3bQUw4ht6RgvtFAgKpcaanVkH9vrt7BBGiJqMHR6jgGwOsq+urUhfGXegNp2NsBYdQKLSCLkZf&#xA;SBmaDq0OC+eRWPt0o9WR17GVZtQXDreDTJMkk1b3xB867fG5w+breLYKfPT7/GV8PWy2uympP/Z1&#xA;2rdbpW5v5s0TiIhz/DPDLz6jQ8VMJ3cmE8SgIMuX7OT7A1diPctXPJwUpMtVCrIq5f8G1Q8AAAD/&#xA;/wMAUEsBAi0AFAAGAAgAAAAhALaDOJL+AAAA4QEAABMAAAAAAAAAAAAAAAAAAAAAAFtDb250ZW50&#xA;X1R5cGVzXS54bWxQSwECLQAUAAYACAAAACEAOP0h/9YAAACUAQAACwAAAAAAAAAAAAAAAAAvAQAA&#xA;X3JlbHMvLnJlbHNQSwECLQAUAAYACAAAACEACxY+CS8CAACiBAAADgAAAAAAAAAAAAAAAAAuAgAA&#xA;ZHJzL2Uyb0RvYy54bWxQSwECLQAUAAYACAAAACEAqJYgPt4AAAAJAQAADwAAAAAAAAAAAAAAAACJ&#xA;BAAAZHJzL2Rvd25yZXYueG1sUEsFBgAAAAAEAAQA8wAAAJQFAAAAAA==&#xA;" filled="f" stroked="f"><v:textbox style="mso-fit-shape-to-text:t"><w:txbxContent><w:p w14:paraId="7904E301" w14:textId="5B745E1E" w:rsidR="00806D19" w:rsidRPr="00806D19" w:rsidRDefault="00806D19" w:rsidP="00806D19"><w:pPr><w:rPr><w:b/><w:bCs/><w:color w:val="102744"/></w:rPr></w:pPr><w:r w:rsidRPr="00806D19"><w:rPr><w:b/><w:bCs/><w:color w:val="102744"/></w:rPr><w:t>BILL TO:</w:t></w:r></w:p><w:p w14:paraId="4B8587FC" w14:textId="77777777" w:rsidR="00806D19" w:rsidRDefault="00806D19" w:rsidP="00806D19"><w:r w:rsidRPr="00806D19"><w:rPr><w:b/><w:bCs/><w:color w:val="102744"/></w:rPr><w:t>Customer Name:</w:t></w:r><w:r w:rsidRPr="00806D19"><w:rPr><w:color w:val="102744"/></w:rPr><w:t xml:space="preserve"> </w:t></w:r><w:r><w:t>Rushabh Chaudhary</w:t></w:r></w:p><w:p w14:paraId="36CB2F5B" w14:textId="6A313903" w:rsidR="00806D19" w:rsidRDefault="00806D19" w:rsidP="00806D19"><w:r w:rsidRPr="00806D19"><w:rPr><w:b/><w:bCs/></w:rPr><w:t>Customer Email:</w:t></w:r><w:r><w:t xml:space="preserve"> rushab.chaudhary4@gmail.com</w:t></w:r></w:p></w:txbxContent></v:textbox><w10:wrap type="square"/></v:shape></w:pict></mc:Fallback></mc:AlternateContent></w:r><w:r w:rsidR="00D420DF" w:rsidRPr="00806D19"><w:rPr><w:rFonts w:ascii="Georgia" w:hAnsi="Georgia"/><w:b/><w:noProof/><w:sz w:val="24"/></w:rPr><mc:AlternateContent><mc:Choice Requires="wps"><w:drawing><wp:anchor distT="0" distB="0" distL="114300" distR="114300" simplePos="0" relativeHeight="251618816" behindDoc="0" locked="0" layoutInCell="1" allowOverlap="1" wp14:anchorId="360BAC74" wp14:editId="44F54DB8"><wp:simplePos x="0" y="0"/><wp:positionH relativeFrom="column"><wp:posOffset>4833183</wp:posOffset></wp:positionH><wp:positionV relativeFrom="paragraph"><wp:posOffset>125714</wp:posOffset></wp:positionV><wp:extent cx="2520564" cy="641268"/><wp:effectExtent l="0" t="0" r="0" b="6985"/><wp:wrapNone/><wp:docPr id="15" name="Text Box 15"/><wp:cNvGraphicFramePr/><a:graphic xmlns:a="http://schemas.openxmlformats.org/drawingml/2006/main"><a:graphicData uri="http://schemas.microsoft.com/office/word/2010/wordprocessingShape"><wps:wsp><wps:cNvSpPr txBox="1"/><wps:spPr><a:xfrm><a:off x="0" y="0"/><a:ext cx="2520564" cy="641268"/></a:xfrm><a:prstGeom prst="rect"><a:avLst/></a:prstGeom><a:noFill/><a:ln w="6350"><a:noFill/></a:ln></wps:spPr><wps:txbx><w:txbxContent><w:p w14:paraId="5CE76535" w14:textId="34228B74" w:rsidR="00D420DF" w:rsidRPr="00D420DF" w:rsidRDefault="00D420DF"><w:pPr><w:rPr><w:color w:val="102744"/><w:sz w:val="20"/><w:szCs w:val="20"/></w:rPr></w:pPr><w:r w:rsidRPr="00D420DF"><w:rPr><w:b/><w:bCs/><w:color w:val="102744"/></w:rPr><w:t>Invoice</w:t></w:r><w:r w:rsidRPr="00D420DF"><w:rPr><w:b/><w:bCs/><w:color w:val="102744"/><w:spacing w:val="-6"/></w:rPr><w:t xml:space="preserve"> </w:t></w:r><w:r w:rsidRPr="00D420DF"><w:rPr><w:b/><w:bCs/><w:color w:val="102744"/></w:rPr><w:t>No:</w:t></w:r><w:r w:rsidRPr="00D420DF"><w:rPr><w:color w:val="102744"/><w:spacing w:val="-5"/></w:rPr><w:t xml:space="preserve"> </w:t></w:r><w:r w:rsidRPr="00D420DF"><w:rPr><w:color w:val="102744"/><w:spacing w:val="-2"/></w:rPr><w:t>2025/MCG/1088</w:t></w:r></w:p><w:p w14:paraId="7B631267" w14:textId="7D792519" w:rsidR="003E2235" w:rsidRPr="00D420DF" w:rsidRDefault="003E2235"><w:pPr><w:rPr><w:color w:val="102744"/><w:sz w:val="20"/><w:szCs w:val="20"/></w:rPr></w:pPr><w:r w:rsidRPr="00D420DF"><w:rPr><w:b/><w:bCs/><w:color w:val="102744"/><w:sz w:val="20"/><w:szCs w:val="20"/></w:rPr><w:t>GST:</w:t></w:r><w:r w:rsidRPr="00D420DF"><w:rPr><w:color w:val="102744"/><w:sz w:val="20"/><w:szCs w:val="20"/></w:rPr><w:t xml:space="preserve"> 09AAOCP5868J1ZI</w:t></w:r><w:r w:rsidRPr="00D420DF"><w:rPr><w:color w:val="102744"/><w:sz w:val="20"/><w:szCs w:val="20"/></w:rPr><w:cr/></w:r></w:p></w:txbxContent></wps:txbx><wps:bodyPr rot="0" spcFirstLastPara="0" vertOverflow="overflow" horzOverflow="overflow" vert="horz" wrap="square" lIns="91440" tIns="45720" rIns="91440" bIns="45720" numCol="1" spcCol="0" rtlCol="0" fromWordArt="0" anchor="t" anchorCtr="0" forceAA="0" compatLnSpc="1"><a:prstTxWarp prst="textNoShape"><a:avLst/></a:prstTxWarp><a:noAutofit/></wps:bodyPr></wps:wsp></a:graphicData></a:graphic><wp14:sizeRelH relativeFrom="margin"><wp14:pctWidth>0</wp14:pctWidth></wp14:sizeRelH><wp14:sizeRelV relativeFrom="margin"><wp14:pctHeight>0</wp14:pctHeight></wp14:sizeRelV></wp:anchor></w:drawing></mc:Choice><mc:Fallback><w:pict><v:shape w14:anchorId="360BAC74" id="Text Box 15" o:spid="_x0000_s1027" type="#_x0000_t202" style="position:absolute;margin-left:380.55pt;margin-top:9.9pt;width:198.45pt;height:50.5pt;z-index:251618816;visibility:visible;mso-wrap-style:square;mso-width-percent:0;mso-height-percent:0;mso-wrap-distance-left:9pt;mso-wrap-distance-top:0;mso-wrap-distance-right:9pt;mso-wrap-distance-bottom:0;mso-position-horizontal:absolute;mso-position-horizontal-relative:text;mso-position-vertical:absolute;mso-position-vertical-relative:text;mso-width-percent:0;mso-height-percent:0;mso-width-relative:margin;mso-height-relative:margin;v-text-anchor:top" o:gfxdata="UEsDBBQABgAIAAAAIQC2gziS/gAAAOEBAAATAAAAW0NvbnRlbnRfVHlwZXNdLnhtbJSRQU7DMBBF&#xA;90jcwfIWJU67QAgl6YK0S0CoHGBkTxKLZGx5TGhvj5O2G0SRWNoz/78nu9wcxkFMGNg6quQqL6RA&#xA;0s5Y6ir5vt9lD1JwBDIwOMJKHpHlpr69KfdHjyxSmriSfYz+USnWPY7AufNIadK6MEJMx9ApD/oD&#xA;OlTrorhX2lFEilmcO2RdNtjC5xDF9pCuTyYBB5bi6bQ4syoJ3g9WQ0ymaiLzg5KdCXlKLjvcW893&#xA;SUOqXwnz5DrgnHtJTxOsQfEKIT7DmDSUCaxw7Rqn8787ZsmRM9e2VmPeBN4uqYvTtW7jvijg9N/y&#xA;JsXecLq0q+WD6m8AAAD//wMAUEsDBBQABgAIAAAAIQA4/SH/1gAAAJQBAAALAAAAX3JlbHMvLnJl&#xA;bHOkkMFqwzAMhu+DvYPRfXGawxijTi+j0GvpHsDYimMaW0Yy2fr2M4PBMnrbUb/Q94l/f/hMi1qR&#xA;JVI2sOt6UJgd+ZiDgffL8ekFlFSbvV0oo4EbChzGx4f9GRdb25HMsYhqlCwG5lrLq9biZkxWOiqY&#xA;22YiTra2kYMu1l1tQD30/bPm3wwYN0x18gb45AdQl1tp5j/sFB2T0FQ7R0nTNEV3j6o9feQzro1i&#xA;OWA14Fm+Q8a1a8+Bvu/d/dMb2JY5uiPbhG/ktn4cqGU/er3pcvwCAAD//wMAUEsDBBQABgAIAAAA&#xA;IQBHOPzUGQIAADMEAAAOAAAAZHJzL2Uyb0RvYy54bWysU01v2zAMvQ/YfxB0X+x4SdYacYqsRYYB&#xA;RVsgHXpWZCk2IImapMTOfv0oOV/odhp2kUmRfiTfo+Z3vVZkL5xvwVR0PMopEYZD3ZptRX+8rj7d&#xA;UOIDMzVTYERFD8LTu8XHD/POlqKABlQtHEEQ48vOVrQJwZZZ5nkjNPMjsMJgUILTLKDrtlntWIfo&#xA;WmVFns+yDlxtHXDhPd4+DEG6SPhSCh6epfQiEFVR7C2k06VzE89sMWfl1jHbtPzYBvuHLjRrDRY9&#xA;Qz2wwMjOtX9A6ZY78CDDiIPOQMqWizQDTjPO302zbpgVaRYkx9szTf7/wfKn/dq+OBL6r9CjgJGQ&#xA;zvrS42Wcp5dOxy92SjCOFB7OtIk+EI6XxbTIp7MJJRxjs8m4mN1EmOzyt3U+fBOgSTQq6lCWxBbb&#xA;P/owpJ5SYjEDq1apJI0ypEPQz9M8/XCOILgyWOPSa7RCv+lJW1/NsYH6gOM5GJT3lq9a7OGR+fDC&#xA;HEqNE+H6hmc8pAKsBUeLkgbcr7/dx3xUAKOUdLg6FfU/d8wJStR3g9rcjieTuGvJmUy/FOi468jm&#xA;OmJ2+h5wO8f4UCxPZswP6mRKB/oNt3wZq2KIGY61KxpO5n0YFhpfCRfLZUrC7bIsPJq15RE6shoZ&#xA;fu3fmLNHGQIK+ASnJWPlOzWG3EGP5S6AbJNUkeeB1SP9uJlJ7OMriqt/7aesy1tf/AYAAP//AwBQ&#xA;SwMEFAAGAAgAAAAhALBrv+vhAAAACwEAAA8AAABkcnMvZG93bnJldi54bWxMj0FLw0AQhe+C/2GZ&#xA;gje7SaA1xmxKCRRB9NDai7dJdpqEZndjdttGf73Tk73N4328eS9fTaYXZxp956yCeB6BIFs73dlG&#xA;wf5z85iC8AGtxt5ZUvBDHlbF/V2OmXYXu6XzLjSCQ6zPUEEbwpBJ6euWDPq5G8iyd3CjwcBybKQe&#xA;8cLhppdJFC2lwc7yhxYHKluqj7uTUfBWbj5wWyUm/e3L1/fDevjefy2UephN6xcQgabwD8O1PleH&#xA;gjtV7mS1F72Cp2UcM8rGM0+4AvEi5XUVX0mUgixyebuh+AMAAP//AwBQSwECLQAUAAYACAAAACEA&#xA;toM4kv4AAADhAQAAEwAAAAAAAAAAAAAAAAAAAAAAW0NvbnRlbnRfVHlwZXNdLnhtbFBLAQItABQA&#xA;BgAIAAAAIQA4/SH/1gAAAJQBAAALAAAAAAAAAAAAAAAAAC8BAABfcmVscy8ucmVsc1BLAQItABQA&#xA;BgAIAAAAIQBHOPzUGQIAADMEAAAOAAAAAAAAAAAAAAAAAC4CAABkcnMvZTJvRG9jLnhtbFBLAQIt&#xA;ABQABgAIAAAAIQCwa7/r4QAAAAsBAAAPAAAAAAAAAAAAAAAAAHMEAABkcnMvZG93bnJldi54bWxQ&#xA;SwUGAAAAAAQABADzAAAAgQUAAAAA&#xA;" filled="f" stroked="f" strokeweight=".5pt"><v:textbox><w:txbxContent><w:p w14:paraId="5CE76535" w14:textId="34228B74" w:rsidR="00D420DF" w:rsidRPr="00D420DF" w:rsidRDefault="00D420DF"><w:pPr><w:rPr><w:color w:val="102744"/><w:sz w:val="20"/><w:szCs w:val="20"/></w:rPr></w:pPr><w:r w:rsidRPr="00D420DF"><w:rPr><w:b/><w:bCs/><w:color w:val="102744"/></w:rPr><w:t>Invoice</w:t></w:r><w:r w:rsidRPr="00D420DF"><w:rPr><w:b/><w:bCs/><w:color w:val="102744"/><w:spacing w:val="-6"/></w:rPr><w:t xml:space="preserve"> </w:t></w:r><w:r w:rsidRPr="00D420DF"><w:rPr><w:b/><w:bCs/><w:color w:val="102744"/></w:rPr><w:t>No:</w:t></w:r><w:r w:rsidRPr="00D420DF"><w:rPr><w:color w:val="102744"/><w:spacing w:val="-5"/></w:rPr><w:t xml:space="preserve"> </w:t></w:r><w:r w:rsidRPr="00D420DF"><w:rPr><w:color w:val="102744"/><w:spacing w:val="-2"/></w:rPr><w:t>2025/MCG/1088</w:t></w:r></w:p><w:p w14:paraId="7B631267" w14:textId="7D792519" w:rsidR="003E2235" w:rsidRPr="00D420DF" w:rsidRDefault="003E2235"><w:pPr><w:rPr><w:color w:val="102744"/><w:sz w:val="20"/><w:szCs w:val="20"/></w:rPr></w:pPr><w:r w:rsidRPr="00D420DF"><w:rPr><w:b/><w:bCs/><w:color w:val="102744"/><w:sz w:val="20"/><w:szCs w:val="20"/></w:rPr><w:t>GST:</w:t></w:r><w:r w:rsidRPr="00D420DF"><w:rPr><w:color w:val="102744"/><w:sz w:val="20"/><w:szCs w:val="20"/></w:rPr><w:t xml:space="preserve"> 09AAOCP5868J1ZI</w:t></w:r><w:r w:rsidRPr="00D420DF"><w:rPr><w:color w:val="102744"/><w:sz w:val="20"/><w:szCs w:val="20"/></w:rPr><w:cr/></w:r></w:p></w:txbxContent></v:textbox></v:shape></w:pict></mc:Fallback></mc:AlternateContent></w:r></w:p><w:p w14:paraId="646E5335" w14:textId="7EF52B60" w:rsidR="00AD3C9A" w:rsidRPr="00806D19" w:rsidRDefault="00AD3C9A" w:rsidP="00806D19"><w:pPr><w:pStyle w:val="BodyText"/><w:tabs><w:tab w:val="left" w:pos="1833"/></w:tabs><w:rPr><w:rFonts w:ascii="Georgia" w:hAnsi="Georgia"/><w:b/><w:sz w:val="24"/></w:rPr></w:pPr></w:p><w:p w14:paraId="777B02A6" w14:textId="52E3C908" w:rsidR="00AD3C9A" w:rsidRPr="00806D19" w:rsidRDefault="00AD3C9A"><w:pPr><w:pStyle w:val="BodyText"/><w:rPr><w:rFonts w:ascii="Georgia" w:hAnsi="Georgia"/><w:b/><w:sz w:val="24"/></w:rPr></w:pPr></w:p><w:p w14:paraId="34C9C3A1" w14:textId="5CB2A5C6" w:rsidR="00AD3C9A" w:rsidRPr="00806D19" w:rsidRDefault="00AD3C9A"><w:pPr><w:pStyle w:val="BodyText"/><w:spacing w:before="93"/><w:rPr><w:rFonts w:ascii="Georgia" w:hAnsi="Georgia"/><w:b/><w:sz w:val="24"/></w:rPr></w:pPr></w:p><w:p w14:paraId="6BDBC7BF" w14:textId="2F00043D" w:rsidR="00AD3C9A" w:rsidRPr="00806D19" w:rsidRDefault="00AD3C9A"><w:pPr><w:pStyle w:val="BodyText"/><w:spacing w:before="95"/><w:rPr><w:rFonts w:ascii="Georgia" w:hAnsi="Georgia"/><w:sz w:val="20"/></w:rPr></w:pPr></w:p><w:tbl><w:tblPr><w:tblStyle w:val="TableGrid"/><w:tblW w:w="0" w:type="auto"/><w:tblInd w:w="718" w:type="dxa"/><w:tblLayout w:type="fixed"/><w:tblLook w:val="0620" w:firstRow="1" w:lastRow="0" w:firstColumn="0" w:lastColumn="0" w:noHBand="1" w:noVBand="1"/></w:tblPr><w:tblGrid><w:gridCol w:w="3501"/><w:gridCol w:w="2727"/><w:gridCol w:w="1916"/><w:gridCol w:w="2323"/></w:tblGrid><w:tr w:rsidR="00BE04BE" w:rsidRPr="00806D19" w14:paraId="6B1A6B09" w14:textId="77777777" w:rsidTr="00BE04BE"><w:trPr><w:trHeight w:val="760"/></w:trPr><w:tc><w:tcPr><w:tcW w:w="3501" w:type="dxa"/><w:shd w:val="clear" w:color="auto" w:fill="996633"/></w:tcPr><w:p w14:paraId="698AE617" w14:textId="614107A1" w:rsidR="00BE04BE" w:rsidRPr="00806D19" w:rsidRDefault="00BE04BE" w:rsidP="00BE04BE"><w:pPr><w:pStyle w:val="TableParagraph"/><w:spacing w:before="202"/><w:ind w:left="106"/><w:rPr><w:b/><w:color w:val="FFFFFF" w:themeColor="background1"/><w:sz w:val="24"/></w:rPr></w:pPr><w:r w:rsidRPr="00C55CCC"><w:rPr><w:rFonts w:cs="Times New Roman"/><w:b/><w:color w:val="FFFFFF" w:themeColor="background1"/><w:sz w:val="24"/></w:rPr><w:t>ITEM</w:t></w:r></w:p></w:tc><w:tc><w:tcPr><w:tcW w:w="2727" w:type="dxa"/><w:shd w:val="clear" w:color="auto" w:fill="996633"/></w:tcPr><w:p w14:paraId="10A9FC5D" w14:textId="35904EB8" w:rsidR="00BE04BE" w:rsidRPr="00806D19" w:rsidRDefault="00BE04BE" w:rsidP="00BE04BE"><w:pPr><w:pStyle w:val="TableParagraph"/><w:spacing w:before="202"/><w:rPr><w:b/><w:color w:val="FFFFFF" w:themeColor="background1"/><w:sz w:val="24"/></w:rPr></w:pPr><w:r><w:rPr><w:b/><w:color w:val="FFFFFF" w:themeColor="background1"/><w:sz w:val="24"/></w:rPr><w:t>Unit Price</w:t></w:r></w:p></w:tc><w:tc><w:tcPr><w:tcW w:w="1916" w:type="dxa"/><w:shd w:val="clear" w:color="auto" w:fill="996633"/></w:tcPr><w:p w14:paraId="644346DD" w14:textId="7C28B14C" w:rsidR="00BE04BE" w:rsidRPr="00806D19" w:rsidRDefault="00BE04BE" w:rsidP="00BE04BE"><w:pPr><w:pStyle w:val="TableParagraph"/><w:spacing w:before="202"/><w:ind w:left="66"/><w:rPr><w:b/><w:color w:val="FFFFFF" w:themeColor="background1"/><w:sz w:val="24"/></w:rPr></w:pPr><w:r w:rsidRPr="00806D19"><w:rPr><w:b/><w:color w:val="FFFFFF" w:themeColor="background1"/><w:sz w:val="24"/></w:rPr><w:t>GST</w:t></w:r><w:r><w:rPr><w:b/><w:color w:val="FFFFFF" w:themeColor="background1"/><w:sz w:val="24"/></w:rPr><w:t xml:space="preserve"> </w:t></w:r><w:r w:rsidRPr="00806D19"><w:rPr><w:b/><w:color w:val="FFFFFF" w:themeColor="background1"/><w:sz w:val="24"/></w:rPr><w:t>(18%)</w:t></w:r></w:p></w:tc><w:tc><w:tcPr><w:tcW w:w="2323" w:type="dxa"/><w:shd w:val="clear" w:color="auto" w:fill="996633"/></w:tcPr><w:p w14:paraId="04026647" w14:textId="36279B80" w:rsidR="00BE04BE" w:rsidRPr="00806D19" w:rsidRDefault="00BE04BE" w:rsidP="00BE04BE"><w:pPr><w:pStyle w:val="TableParagraph"/><w:spacing w:before="202"/><w:ind w:left="56"/><w:rPr><w:b/><w:color w:val="FFFFFF" w:themeColor="background1"/><w:sz w:val="24"/></w:rPr></w:pPr><w:r w:rsidRPr="00806D19"><w:rPr><w:b/><w:color w:val="FFFFFF" w:themeColor="background1"/><w:sz w:val="24"/></w:rPr><w:t>AMMOUNT</w:t></w:r></w:p></w:tc></w:tr><w:tr w:rsidR="00BE04BE" w:rsidRPr="00806D19" w14:paraId="79681BA4" w14:textId="77777777" w:rsidTr="00BE04BE"><w:trPr><w:trHeight w:val="704"/></w:trPr><w:tc><w:tcPr><w:tcW w:w="3501" w:type="dxa"/></w:tcPr><w:p w14:paraId="6F892FC7" w14:textId="1D35B60E" w:rsidR="00BE04BE" w:rsidRPr="00806D19" w:rsidRDefault="00BE04BE" w:rsidP="00BE04BE"><w:pPr><w:pStyle w:val="TableParagraph"/><w:spacing w:before="234"/><w:ind w:left="57"/><w:rPr><w:rFonts w:ascii="Georgia" w:hAnsi="Georgia"/><w:sz w:val="21"/></w:rPr></w:pPr><w:r><w:rPr><w:rFonts w:ascii="Times New Roman" w:hAnsi="Times New Roman" w:cs="Times New Roman"/><w:b/><w:bCs/><w:sz w:val="32"/><w:szCs w:val="32"/></w:rPr><w:t>Course 01</w:t></w:r></w:p></w:tc><w:tc><w:tcPr><w:tcW w:w="2727" w:type="dxa"/></w:tcPr><w:p w14:paraId="7CFADAB4" w14:textId="3095EFA8" w:rsidR="00BE04BE" w:rsidRPr="00806D19" w:rsidRDefault="00BE04BE" w:rsidP="00BE04BE"><w:pPr><w:pStyle w:val="TableParagraph"/><w:spacing w:before="234"/><w:ind w:left="372"/><w:jc w:val="left"/><w:rPr><w:rFonts w:ascii="Georgia" w:hAnsi="Georgia"/><w:sz w:val="21"/></w:rPr></w:pPr><w:r><w:rPr><w:rFonts w:ascii="Times New Roman" w:hAnsi="Times New Roman" w:cs="Times New Roman"/><w:b/><w:bCs/><w:sz w:val="32"/><w:szCs w:val="32"/></w:rPr><w:t>21,186.44</w:t></w:r></w:p></w:tc><w:tc><w:tcPr><w:tcW w:w="1916" w:type="dxa"/></w:tcPr><w:p w14:paraId="3EA51D82" w14:textId="0317DF32" w:rsidR="00BE04BE" w:rsidRPr="00806D19" w:rsidRDefault="00BE04BE" w:rsidP="00BE04BE"><w:pPr><w:pStyle w:val="TableParagraph"/><w:spacing w:before="234"/><w:ind w:left="1" w:right="31"/><w:rPr><w:rFonts w:ascii="Georgia" w:hAnsi="Georgia"/><w:sz w:val="21"/></w:rPr></w:pPr><w:r><w:rPr><w:rFonts w:ascii="Times New Roman" w:hAnsi="Times New Roman" w:cs="Times New Roman"/><w:b/><w:bCs/><w:sz w:val="32"/><w:szCs w:val="32"/></w:rPr><w:t>3,813.56</w:t></w:r></w:p></w:tc><w:tc><w:tcPr><w:tcW w:w="2323" w:type="dxa"/></w:tcPr><w:p w14:paraId="5F69D047" w14:textId="45DA2880" w:rsidR="00BE04BE" w:rsidRPr="00806D19" w:rsidRDefault="00BE04BE" w:rsidP="00BE04BE"><w:pPr><w:pStyle w:val="TableParagraph"/><w:spacing w:before="234"/><w:ind w:left="49" w:right="1"/><w:rPr><w:rFonts w:ascii="Georgia" w:hAnsi="Georgia"/><w:sz w:val="21"/></w:rPr></w:pPr><w:r><w:rPr><w:rFonts w:ascii="Times New Roman" w:hAnsi="Times New Roman" w:cs="Times New Roman"/><w:b/><w:bCs/><w:sz w:val="32"/><w:szCs w:val="32"/></w:rPr><w:t>25,000</w:t></w:r></w:p></w:tc></w:tr><w:tr w:rsidR="00BE04BE" w:rsidRPr="00806D19" w14:paraId="78CEBBAF" w14:textId="77777777" w:rsidTr="00BE04BE"><w:trPr><w:trHeight w:val="565"/></w:trPr><w:tc><w:tcPr><w:tcW w:w="3501" w:type="dxa"/></w:tcPr><w:p w14:paraId="29F95957" w14:textId="5D509E34" w:rsidR="00BE04BE" w:rsidRPr="00806D19" w:rsidRDefault="00BE04BE" w:rsidP="00BE04BE"><w:pPr><w:pStyle w:val="TableParagraph"/><w:ind w:left="57"/><w:rPr><w:rFonts w:ascii="Georgia" w:hAnsi="Georgia"/><w:sz w:val="21"/></w:rPr></w:pPr><w:r><w:rPr><w:rFonts w:ascii="Times New Roman" w:hAnsi="Times New Roman" w:cs="Times New Roman"/><w:b/><w:bCs/><w:sz w:val="32"/><w:szCs w:val="32"/></w:rPr><w:t>Course 02</w:t></w:r></w:p></w:tc><w:tc><w:tcPr><w:tcW w:w="2727" w:type="dxa"/></w:tcPr><w:p w14:paraId="5DE534B2" w14:textId="78D20A5A" w:rsidR="00BE04BE" w:rsidRPr="00806D19" w:rsidRDefault="00BE04BE" w:rsidP="00BE04BE"><w:pPr><w:pStyle w:val="TableParagraph"/><w:ind w:left="372"/><w:jc w:val="left"/><w:rPr><w:rFonts w:ascii="Georgia" w:hAnsi="Georgia"/><w:sz w:val="21"/></w:rPr></w:pPr><w:r><w:rPr><w:rFonts w:ascii="Times New Roman" w:hAnsi="Times New Roman" w:cs="Times New Roman"/><w:b/><w:bCs/><w:sz w:val="32"/><w:szCs w:val="32"/></w:rPr><w:t>29,661.02</w:t></w:r></w:p></w:tc><w:tc><w:tcPr><w:tcW w:w="1916" w:type="dxa"/></w:tcPr><w:p w14:paraId="3D23858D" w14:textId="2CE41A41" w:rsidR="00BE04BE" w:rsidRPr="00806D19" w:rsidRDefault="00BE04BE" w:rsidP="00BE04BE"><w:pPr><w:pStyle w:val="TableParagraph"/><w:ind w:right="31"/><w:rPr><w:rFonts w:ascii="Georgia" w:hAnsi="Georgia"/><w:sz w:val="21"/></w:rPr></w:pPr><w:r><w:rPr><w:rFonts w:ascii="Times New Roman" w:hAnsi="Times New Roman" w:cs="Times New Roman"/><w:b/><w:bCs/><w:sz w:val="32"/><w:szCs w:val="32"/></w:rPr><w:t>5,338.98</w:t></w:r></w:p></w:tc><w:tc><w:tcPr><w:tcW w:w="2323" w:type="dxa"/></w:tcPr><w:p w14:paraId="16C759DA" w14:textId="45CFF752" w:rsidR="00BE04BE" w:rsidRPr="00806D19" w:rsidRDefault="00BE04BE" w:rsidP="00BE04BE"><w:pPr><w:pStyle w:val="TableParagraph"/><w:ind w:left="49"/><w:rPr><w:rFonts w:ascii="Georgia" w:hAnsi="Georgia"/><w:sz w:val="21"/></w:rPr></w:pPr><w:r><w:rPr><w:rFonts w:ascii="Times New Roman" w:hAnsi="Times New Roman" w:cs="Times New Roman"/><w:b/><w:bCs/><w:sz w:val="32"/><w:szCs w:val="32"/></w:rPr><w:t>35,000</w:t></w:r></w:p></w:tc></w:tr><w:tr w:rsidR="00BE04BE" w:rsidRPr="00806D19" w14:paraId="119CE26F" w14:textId="77777777" w:rsidTr="00BE04BE"><w:trPr><w:trHeight w:val="611"/></w:trPr><w:tc><w:tcPr><w:tcW w:w="3501" w:type="dxa"/></w:tcPr><w:p w14:paraId="2E033152" w14:textId="564FD81C" w:rsidR="00BE04BE" w:rsidRPr="00806D19" w:rsidRDefault="00BE04BE" w:rsidP="00BE04BE"><w:pPr><w:pStyle w:val="TableParagraph"/><w:spacing w:before="165"/><w:ind w:left="57" w:right="1"/><w:rPr><w:rFonts w:ascii="Georgia" w:hAnsi="Georgia"/><w:sz w:val="21"/></w:rPr></w:pPr><w:r><w:rPr><w:rFonts w:ascii="Times New Roman" w:hAnsi="Times New Roman" w:cs="Times New Roman"/><w:b/><w:bCs/><w:sz w:val="32"/><w:szCs w:val="32"/></w:rPr><w:t>Course 03</w:t></w:r></w:p></w:tc><w:tc><w:tcPr><w:tcW w:w="2727" w:type="dxa"/></w:tcPr><w:p w14:paraId="4B87DD4C" w14:textId="50228369" w:rsidR="00BE04BE" w:rsidRPr="00806D19" w:rsidRDefault="00BE04BE" w:rsidP="00BE04BE"><w:pPr><w:pStyle w:val="TableParagraph"/><w:spacing w:before="165"/><w:ind w:left="372"/><w:jc w:val="left"/><w:rPr><w:rFonts w:ascii="Georgia" w:hAnsi="Georgia"/><w:sz w:val="21"/></w:rPr></w:pPr><w:r><w:rPr><w:rFonts w:ascii="Times New Roman" w:hAnsi="Times New Roman" w:cs="Times New Roman"/><w:b/><w:bCs/><w:sz w:val="32"/><w:szCs w:val="32"/></w:rPr><w:t>8,474.58</w:t></w:r></w:p></w:tc><w:tc><w:tcPr><w:tcW w:w="1916" w:type="dxa"/></w:tcPr><w:p w14:paraId="36418387" w14:textId="571839CC" w:rsidR="00BE04BE" w:rsidRPr="00806D19" w:rsidRDefault="00BE04BE" w:rsidP="00BE04BE"><w:pPr><w:pStyle w:val="TableParagraph"/><w:spacing w:before="165"/><w:ind w:left="1" w:right="31"/><w:rPr><w:rFonts w:ascii="Georgia" w:hAnsi="Georgia"/><w:sz w:val="21"/></w:rPr></w:pPr><w:r><w:rPr><w:rFonts w:ascii="Times New Roman" w:hAnsi="Times New Roman" w:cs="Times New Roman"/><w:b/><w:bCs/><w:sz w:val="32"/><w:szCs w:val="32"/></w:rPr><w:t>1,525.42</w:t></w:r></w:p></w:tc><w:tc><w:tcPr><w:tcW w:w="2323" w:type="dxa"/></w:tcPr><w:p w14:paraId="0A5FA07F" w14:textId="576E1B1A" w:rsidR="00BE04BE" w:rsidRPr="00806D19" w:rsidRDefault="00BE04BE" w:rsidP="00BE04BE"><w:pPr><w:pStyle w:val="TableParagraph"/><w:spacing w:before="165"/><w:ind w:left="49" w:right="1"/><w:rPr><w:rFonts w:ascii="Georgia" w:hAnsi="Georgia"/><w:sz w:val="21"/></w:rPr></w:pPr><w:r><w:rPr><w:rFonts w:ascii="Times New Roman" w:hAnsi="Times New Roman" w:cs="Times New Roman"/><w:b/><w:bCs/><w:sz w:val="32"/><w:szCs w:val="32"/></w:rPr><w:t>10,000</w:t></w:r></w:p></w:tc></w:tr><w:tr w:rsidR="00BE04BE" w:rsidRPr="00806D19" w14:paraId="7D51448E" w14:textId="77777777" w:rsidTr="00BE04BE"><w:trPr><w:trHeight w:val="611"/></w:trPr><w:tc><w:tcPr><w:tcW w:w="3501" w:type="dxa"/></w:tcPr><w:p w14:paraId="7F4592F2" w14:textId="740993FB" w:rsidR="00BE04BE" w:rsidRPr="00806D19" w:rsidRDefault="00BE04BE" w:rsidP="00BE04BE"><w:pPr><w:pStyle w:val="TableParagraph"/><w:spacing w:before="165"/><w:ind w:left="57" w:right="1"/><w:rPr><w:rFonts w:ascii="Georgia" w:hAnsi="Georgia"/><w:spacing w:val="-5"/><w:w w:val="85"/><w:sz w:val="21"/></w:rPr></w:pPr></w:p></w:tc><w:tc><w:tcPr><w:tcW w:w="2727" w:type="dxa"/></w:tcPr><w:p w14:paraId="2B23456D" w14:textId="6795AC8D" w:rsidR="00BE04BE" w:rsidRPr="00806D19" w:rsidRDefault="00BE04BE" w:rsidP="00BE04BE"><w:pPr><w:pStyle w:val="TableParagraph"/><w:spacing w:before="165"/><w:ind w:left="372"/><w:jc w:val="left"/><w:rPr><w:rFonts w:ascii="Georgia" w:hAnsi="Georgia"/><w:sz w:val="21"/></w:rPr></w:pPr></w:p></w:tc><w:tc><w:tcPr><w:tcW w:w="1916" w:type="dxa"/></w:tcPr><w:p w14:paraId="032B35A7" w14:textId="0EE7A445" w:rsidR="00BE04BE" w:rsidRPr="00806D19" w:rsidRDefault="00BE04BE" w:rsidP="00BE04BE"><w:pPr><w:pStyle w:val="TableParagraph"/><w:spacing w:before="165"/><w:ind w:left="1" w:right="31"/><w:rPr><w:rFonts w:ascii="Georgia" w:hAnsi="Georgia"/><w:spacing w:val="-4"/><w:sz w:val="21"/></w:rPr></w:pPr></w:p></w:tc><w:tc><w:tcPr><w:tcW w:w="2323" w:type="dxa"/></w:tcPr><w:p w14:paraId="2BB5ECFC" w14:textId="2A6F67A3" w:rsidR="00BE04BE" w:rsidRPr="00806D19" w:rsidRDefault="00BE04BE" w:rsidP="00BE04BE"><w:pPr><w:pStyle w:val="TableParagraph"/><w:spacing w:before="165"/><w:ind w:left="49" w:right="1"/><w:rPr><w:rFonts w:ascii="Georgia" w:hAnsi="Georgia"/><w:spacing w:val="-4"/><w:sz w:val="21"/></w:rPr></w:pPr></w:p></w:tc></w:tr><w:tr w:rsidR="00BE04BE" w:rsidRPr="00806D19" w14:paraId="12473FFC" w14:textId="77777777" w:rsidTr="00BE04BE"><w:trPr><w:trHeight w:val="611"/></w:trPr><w:tc><w:tcPr><w:tcW w:w="3501" w:type="dxa"/></w:tcPr><w:p w14:paraId="5ABC5826" w14:textId="137AAF32" w:rsidR="00BE04BE" w:rsidRPr="00806D19" w:rsidRDefault="00BE04BE" w:rsidP="00BE04BE"><w:pPr><w:pStyle w:val="TableParagraph"/><w:spacing w:before="165"/><w:ind w:left="57" w:right="1"/><w:rPr><w:rFonts w:ascii="Georgia" w:hAnsi="Georgia"/><w:spacing w:val="-5"/><w:w w:val="85"/><w:sz w:val="21"/></w:rPr></w:pPr></w:p></w:tc><w:tc><w:tcPr><w:tcW w:w="2727" w:type="dxa"/></w:tcPr><w:p w14:paraId="068E9BA0" w14:textId="5AA1FD2E" w:rsidR="00BE04BE" w:rsidRPr="00806D19" w:rsidRDefault="00BE04BE" w:rsidP="00BE04BE"><w:pPr><w:pStyle w:val="TableParagraph"/><w:spacing w:before="165"/><w:ind w:left="372"/><w:jc w:val="left"/><w:rPr><w:rFonts w:ascii="Georgia" w:hAnsi="Georgia"/><w:sz w:val="21"/></w:rPr></w:pPr></w:p></w:tc><w:tc><w:tcPr><w:tcW w:w="1916" w:type="dxa"/></w:tcPr><w:p w14:paraId="27F504B2" w14:textId="5945823B" w:rsidR="00BE04BE" w:rsidRPr="00806D19" w:rsidRDefault="00BE04BE" w:rsidP="00BE04BE"><w:pPr><w:pStyle w:val="TableParagraph"/><w:spacing w:before="165"/><w:ind w:left="1" w:right="31"/><w:rPr><w:rFonts w:ascii="Georgia" w:hAnsi="Georgia"/><w:spacing w:val="-4"/><w:sz w:val="21"/></w:rPr></w:pPr></w:p></w:tc><w:tc><w:tcPr><w:tcW w:w="2323" w:type="dxa"/></w:tcPr><w:p w14:paraId="7DC1E3A6" w14:textId="2E7F0091" w:rsidR="00BE04BE" w:rsidRPr="00806D19" w:rsidRDefault="00BE04BE" w:rsidP="00BE04BE"><w:pPr><w:pStyle w:val="TableParagraph"/><w:spacing w:before="165"/><w:ind w:left="49" w:right="1"/><w:rPr><w:rFonts w:ascii="Georgia" w:hAnsi="Georgia"/><w:spacing w:val="-4"/><w:sz w:val="21"/></w:rPr></w:pPr></w:p></w:tc></w:tr><w:tr w:rsidR="00BE04BE" w:rsidRPr="00806D19" w14:paraId="32299A94" w14:textId="77777777" w:rsidTr="00BE04BE"><w:trPr><w:trHeight w:val="611"/></w:trPr><w:tc><w:tcPr><w:tcW w:w="3501" w:type="dxa"/></w:tcPr><w:p w14:paraId="633D16F9" w14:textId="7516A372" w:rsidR="00BE04BE" w:rsidRPr="00806D19" w:rsidRDefault="00BE04BE" w:rsidP="00BE04BE"><w:pPr><w:pStyle w:val="TableParagraph"/><w:spacing w:before="165"/><w:ind w:left="57" w:right="1"/><w:rPr><w:rFonts w:ascii="Georgia" w:hAnsi="Georgia"/><w:spacing w:val="-5"/><w:w w:val="85"/><w:sz w:val="21"/></w:rPr></w:pPr></w:p></w:tc><w:tc><w:tcPr><w:tcW w:w="2727" w:type="dxa"/></w:tcPr><w:p w14:paraId="39A7303D" w14:textId="10179E0A" w:rsidR="00BE04BE" w:rsidRPr="00806D19" w:rsidRDefault="00BE04BE" w:rsidP="00BE04BE"><w:pPr><w:pStyle w:val="TableParagraph"/><w:spacing w:before="165"/><w:ind w:left="372"/><w:jc w:val="left"/><w:rPr><w:rFonts w:ascii="Georgia" w:hAnsi="Georgia"/><w:sz w:val="21"/></w:rPr></w:pPr></w:p></w:tc><w:tc><w:tcPr><w:tcW w:w="1916" w:type="dxa"/></w:tcPr><w:p w14:paraId="5DF26F92" w14:textId="6216646D" w:rsidR="00BE04BE" w:rsidRPr="00806D19" w:rsidRDefault="00BE04BE" w:rsidP="00BE04BE"><w:pPr><w:pStyle w:val="TableParagraph"/><w:spacing w:before="165"/><w:ind w:left="1" w:right="31"/><w:rPr><w:rFonts w:ascii="Georgia" w:hAnsi="Georgia"/><w:spacing w:val="-4"/><w:sz w:val="21"/></w:rPr></w:pPr></w:p></w:tc><w:tc><w:tcPr><w:tcW w:w="2323" w:type="dxa"/></w:tcPr><w:p w14:paraId="38AF24F5" w14:textId="649FD0B4" w:rsidR="00BE04BE" w:rsidRPr="00806D19" w:rsidRDefault="00BE04BE" w:rsidP="00BE04BE"><w:pPr><w:pStyle w:val="TableParagraph"/><w:spacing w:before="165"/><w:ind w:left="49" w:right="1"/><w:rPr><w:rFonts w:ascii="Georgia" w:hAnsi="Georgia"/><w:spacing w:val="-4"/><w:sz w:val="21"/></w:rPr></w:pPr></w:p></w:tc></w:tr></w:tbl><w:p w14:paraId="7FF27B34" w14:textId="2A20E1B4" w:rsidR="00AD3C9A" w:rsidRPr="00806D19" w:rsidRDefault="00AD3C9A"><w:pPr><w:pStyle w:val="BodyText"/><w:rPr><w:rFonts w:ascii="Georgia" w:hAnsi="Georgia"/><w:sz w:val="21"/></w:rPr></w:pPr></w:p><w:p w14:paraId="146D674A" w14:textId="614118D9" w:rsidR="00AD3C9A" w:rsidRPr="00806D19" w:rsidRDefault="00285745"><w:pPr><w:pStyle w:val="BodyText"/><w:rPr><w:rFonts w:ascii="Georgia" w:hAnsi="Georgia"/><w:sz w:val="21"/></w:rPr></w:pPr><w:r w:rsidRPr="00806D19"><w:rPr><w:rFonts w:ascii="Georgia" w:hAnsi="Georgia"/><w:noProof/></w:rPr><mc:AlternateContent><mc:Choice Requires="wps"><w:drawing><wp:anchor distT="0" distB="0" distL="0" distR="0" simplePos="0" relativeHeight="251653120" behindDoc="0" locked="0" layoutInCell="1" allowOverlap="1" wp14:anchorId="47E838BE" wp14:editId="03042930"><wp:simplePos x="0" y="0"/><wp:positionH relativeFrom="page"><wp:posOffset>4360460</wp:posOffset></wp:positionH><wp:positionV relativeFrom="paragraph"><wp:posOffset>83204</wp:posOffset></wp:positionV><wp:extent cx="2628900" cy="793750"/><wp:effectExtent l="0" t="0" r="0" b="6350"/><wp:wrapNone/><wp:docPr id="12" name="Textbox 12"/><wp:cNvGraphicFramePr><a:graphicFrameLocks xmlns:a="http://schemas.openxmlformats.org/drawingml/2006/main"/></wp:cNvGraphicFramePr><a:graphic xmlns:a="http://schemas.openxmlformats.org/drawingml/2006/main"><a:graphicData uri="http://schemas.microsoft.com/office/word/2010/wordprocessingShape"><wps:wsp><wps:cNvSpPr txBox="1"><a:spLocks/></wps:cNvSpPr><wps:spPr><a:xfrm><a:off x="0" y="0"/><a:ext cx="2628900" cy="793750"/></a:xfrm><a:prstGeom prst="rect"><a:avLst/></a:prstGeom><a:solidFill><a:schemeClr val="bg1"><a:lumMod val="75000"/></a:schemeClr></a:solidFill></wps:spPr><wps:txbx><w:txbxContent><w:p w14:paraId="2B5D5B4E" w14:textId="1A5316AD" w:rsidR="00BE04BE" w:rsidRPr="00BE04BE" w:rsidRDefault="00285745" w:rsidP="00BE04BE"><w:pPr><w:pStyle w:val="BodyText"/><w:spacing w:before="160" w:line="276" w:lineRule="auto"/><w:jc w:val="both"/><w:rPr><w:color w:val="000000" w:themeColor="text1"/></w:rPr></w:pPr><w:r><w:t xml:space="preserve">       </w:t></w:r><w:r w:rsidR="00BE04BE" w:rsidRPr="00BE04BE"><w:rPr><w:color w:val="000000" w:themeColor="text1"/></w:rPr><w:t xml:space="preserve">SUB TOTAL :      59,322.04          </w:t></w:r></w:p><w:p w14:paraId="37848745" w14:textId="77777777" w:rsidR="00BE04BE" w:rsidRPr="00BE04BE" w:rsidRDefault="00BE04BE" w:rsidP="00BE04BE"><w:pPr><w:pStyle w:val="BodyText"/><w:spacing w:before="160" w:line="276" w:lineRule="auto"/><w:jc w:val="both"/><w:rPr><w:color w:val="000000" w:themeColor="text1"/></w:rPr></w:pPr><w:r w:rsidRPr="00BE04BE"><w:rPr><w:color w:val="000000" w:themeColor="text1"/></w:rPr><w:t xml:space="preserve">       TOTAL GST :      10,677.96          </w:t></w:r></w:p><w:p w14:paraId="666CE57B" w14:textId="724623ED" w:rsidR="00285745" w:rsidRDefault="00285745" w:rsidP="00BE04BE"><w:pPr><w:pStyle w:val="BodyText"/><w:spacing w:before="160" w:line="276" w:lineRule="auto"/><w:jc w:val="both"/></w:pPr></w:p></w:txbxContent></wps:txbx><wps:bodyPr wrap="square" lIns="0" tIns="0" rIns="0" bIns="0" rtlCol="0"><a:noAutofit/></wps:bodyPr></wps:wsp></a:graphicData></a:graphic><wp14:sizeRelH relativeFrom="margin"><wp14:pctWidth>0</wp14:pctWidth></wp14:sizeRelH><wp14:sizeRelV relativeFrom="margin"><wp14:pctHeight>0</wp14:pctHeight></wp14:sizeRelV></wp:anchor></w:drawing></mc:Choice><mc:Fallback><w:pict><v:shape w14:anchorId="47E838BE" id="Textbox 12" o:spid="_x0000_s1028" type="#_x0000_t202" style="position:absolute;margin-left:343.35pt;margin-top:6.55pt;width:207pt;height:62.5pt;z-index:251653120;visibility:visible;mso-wrap-style:square;mso-width-percent:0;mso-height-percent:0;mso-wrap-distance-left:0;mso-wrap-distance-top:0;mso-wrap-distance-right:0;mso-wrap-distance-bottom:0;mso-position-horizontal:absolute;mso-position-horizontal-relative:page;mso-position-vertical:absolute;mso-position-vertical-relative:text;mso-width-percent:0;mso-height-percent:0;mso-width-relative:margin;mso-height-relative:margin;v-text-anchor:top" o:gfxdata="UEsDBBQABgAIAAAAIQC2gziS/gAAAOEBAAATAAAAW0NvbnRlbnRfVHlwZXNdLnhtbJSRQU7DMBBF&#xA;90jcwfIWJU67QAgl6YK0S0CoHGBkTxKLZGx5TGhvj5O2G0SRWNoz/78nu9wcxkFMGNg6quQqL6RA&#xA;0s5Y6ir5vt9lD1JwBDIwOMJKHpHlpr69KfdHjyxSmriSfYz+USnWPY7AufNIadK6MEJMx9ApD/oD&#xA;OlTrorhX2lFEilmcO2RdNtjC5xDF9pCuTyYBB5bi6bQ4syoJ3g9WQ0ymaiLzg5KdCXlKLjvcW893&#xA;SUOqXwnz5DrgnHtJTxOsQfEKIT7DmDSUCaxw7Rqn8787ZsmRM9e2VmPeBN4uqYvTtW7jvijg9N/y&#xA;JsXecLq0q+WD6m8AAAD//wMAUEsDBBQABgAIAAAAIQA4/SH/1gAAAJQBAAALAAAAX3JlbHMvLnJl&#xA;bHOkkMFqwzAMhu+DvYPRfXGawxijTi+j0GvpHsDYimMaW0Yy2fr2M4PBMnrbUb/Q94l/f/hMi1qR&#xA;JVI2sOt6UJgd+ZiDgffL8ekFlFSbvV0oo4EbChzGx4f9GRdb25HMsYhqlCwG5lrLq9biZkxWOiqY&#xA;22YiTra2kYMu1l1tQD30/bPm3wwYN0x18gb45AdQl1tp5j/sFB2T0FQ7R0nTNEV3j6o9feQzro1i&#xA;OWA14Fm+Q8a1a8+Bvu/d/dMb2JY5uiPbhG/ktn4cqGU/er3pcvwCAAD//wMAUEsDBBQABgAIAAAA&#xA;IQDCyKrwwwEAAHkDAAAOAAAAZHJzL2Uyb0RvYy54bWysU9tu2zAMfR+wfxD0vtjNsF6MOMXWosOA&#xA;7gJ0+wBZlmJhkqiJSuz8/Sg5l2J9K/YiUyR1yHNIr24nZ9lORTTgW36xqDlTXkJv/Kblv34+vLvm&#xA;DJPwvbDgVcv3Cvnt+u2b1RgatYQBbK8iIxCPzRhaPqQUmqpCOSgncAFBeQpqiE4kusZN1UcxErqz&#xA;1bKuL6sRYh8iSIVI3vs5yNcFX2sl03etUSVmW069pXLGcnb5rNYr0WyiCIORhzbEK7pwwngqeoK6&#xA;F0mwbTQvoJyRERB0WkhwFWhtpCociM1F/Q+bp0EEVbiQOBhOMuH/g5Xfdk/hR2Rp+gQTDbCQwPAI&#xA;8jeSNtUYsDnkZE2xQcrORCcdXf4SBUYPSdv9SU81JSbJubxcXt/UFJIUu7p5f/WhCF6dX4eI6bMC&#xA;x7LR8kjzKh2I3SOmXF80x5RcDMGa/sFYWy55R9SdjWwnaLrdZm7ebt1X6GcfFaTyM05ZqZxeUJ8h&#xA;FY4zrUwwTd3ETE/d54fZ00G/J4lG2pKW45+tiIoz+8XTGPJKHY14NLqjEZO9g7J4uV8PH7cJtCm8&#xA;zrgHkWm+pbHDLuYFen4vWec/Zv0XAAD//wMAUEsDBBQABgAIAAAAIQAhal813AAAAAsBAAAPAAAA&#xA;ZHJzL2Rvd25yZXYueG1sTI/NTsMwEITvSLyDtUjcqJ0iQkjjVKgVXFFTxNmNt0nU+EexmyZvz+YE&#xA;x50ZzXxbbCfTsxGH0DkrIVkJYGhrpzvbSPg+fjxlwEJUVqveWZQwY4BteX9XqFy7mz3gWMWGUYkN&#xA;uZLQxuhzzkPdolFh5Txa8s5uMCrSOTRcD+pG5abnayFSblRnaaFVHnct1pfqamjkrd3P+6+L9vGw&#xA;q9bT7MfPnxcpHx+m9w2wiFP8C8OCT+hQEtPJXa0OrJeQZukrRcl4ToAtgUQIUk6LkiXAy4L//6H8&#xA;BQAA//8DAFBLAQItABQABgAIAAAAIQC2gziS/gAAAOEBAAATAAAAAAAAAAAAAAAAAAAAAABbQ29u&#xA;dGVudF9UeXBlc10ueG1sUEsBAi0AFAAGAAgAAAAhADj9If/WAAAAlAEAAAsAAAAAAAAAAAAAAAAA&#xA;LwEAAF9yZWxzLy5yZWxzUEsBAi0AFAAGAAgAAAAhAMLIqvDDAQAAeQMAAA4AAAAAAAAAAAAAAAAA&#xA;LgIAAGRycy9lMm9Eb2MueG1sUEsBAi0AFAAGAAgAAAAhACFqXzXcAAAACwEAAA8AAAAAAAAAAAAA&#xA;AAAAHQQAAGRycy9kb3ducmV2LnhtbFBLBQYAAAAABAAEAPMAAAAmBQAAAAA=&#xA;" fillcolor="#bfbfbf [2412]" stroked="f"><v:textbox inset="0,0,0,0"><w:txbxContent><w:p w14:paraId="2B5D5B4E" w14:textId="1A5316AD" w:rsidR="00BE04BE" w:rsidRPr="00BE04BE" w:rsidRDefault="00285745" w:rsidP="00BE04BE"><w:pPr><w:pStyle w:val="BodyText"/><w:spacing w:before="160" w:line="276" w:lineRule="auto"/><w:jc w:val="both"/><w:rPr><w:color w:val="000000" w:themeColor="text1"/></w:rPr></w:pPr><w:r><w:t xml:space="preserve">       </w:t></w:r><w:r w:rsidR="00BE04BE" w:rsidRPr="00BE04BE"><w:rPr><w:color w:val="000000" w:themeColor="text1"/></w:rPr><w:t xml:space="preserve">SUB TOTAL :      59,322.04          </w:t></w:r></w:p><w:p w14:paraId="37848745" w14:textId="77777777" w:rsidR="00BE04BE" w:rsidRPr="00BE04BE" w:rsidRDefault="00BE04BE" w:rsidP="00BE04BE"><w:pPr><w:pStyle w:val="BodyText"/><w:spacing w:before="160" w:line="276" w:lineRule="auto"/><w:jc w:val="both"/><w:rPr><w:color w:val="000000" w:themeColor="text1"/></w:rPr></w:pPr><w:r w:rsidRPr="00BE04BE"><w:rPr><w:color w:val="000000" w:themeColor="text1"/></w:rPr><w:t xml:space="preserve">       TOTAL GST :      10,677.96          </w:t></w:r></w:p><w:p w14:paraId="666CE57B" w14:textId="724623ED" w:rsidR="00285745" w:rsidRDefault="00285745" w:rsidP="00BE04BE"><w:pPr><w:pStyle w:val="BodyText"/><w:spacing w:before="160" w:line="276" w:lineRule="auto"/><w:jc w:val="both"/></w:pPr></w:p></w:txbxContent></v:textbox><w10:wrap anchorx="page"/></v:shape></w:pict></mc:Fallback></mc:AlternateContent></w:r></w:p><w:p w14:paraId="49A8BB2D" w14:textId="31F6B9C2" w:rsidR="00AD3C9A" w:rsidRPr="00285745" w:rsidRDefault="00AD3C9A"><w:pPr><w:pStyle w:val="BodyText"/><w:ind w:left="1359"/><w:rPr><w:rFonts w:ascii="Calibri" w:hAnsi="Calibri" w:cs="Calibri"/><w:b/><w:bCs/></w:rPr></w:pPr></w:p><w:p w14:paraId="42974BD2" w14:textId="387EF1D1" w:rsidR="00A402AC" w:rsidRPr="00FA2309" w:rsidRDefault="0037410B" w:rsidP="00A402AC"><w:pPr><w:pStyle w:val="BodyText"/><w:spacing w:before="226"/><w:ind w:left="1359" w:firstLine="81"/><w:rPr><w:rFonts w:asciiTheme="minorHAnsi" w:hAnsiTheme="minorHAnsi" w:cstheme="minorHAnsi"/><w:b/><w:bCs/></w:rPr></w:pPr><w:r w:rsidRPr="00FA2309"><w:rPr><w:rFonts w:asciiTheme="minorHAnsi" w:hAnsiTheme="minorHAnsi" w:cstheme="minorHAnsi"/><w:b/><w:bCs/><w:noProof/></w:rPr><w:drawing><wp:anchor distT="0" distB="0" distL="114300" distR="114300" simplePos="0" relativeHeight="251654144" behindDoc="1" locked="0" layoutInCell="1" allowOverlap="1" wp14:anchorId="6C5B4BF2" wp14:editId="488162EB"><wp:simplePos x="0" y="0"/><wp:positionH relativeFrom="column"><wp:posOffset>5690235</wp:posOffset></wp:positionH><wp:positionV relativeFrom="paragraph"><wp:posOffset>255880</wp:posOffset></wp:positionV><wp:extent cx="833755" cy="4335771"/><wp:effectExtent l="0" t="0" r="4445" b="8255"/><wp:wrapNone/><wp:docPr id="1393184860" name="Picture 12"/><wp:cNvGraphicFramePr><a:graphicFrameLocks xmlns:a="http://schemas.openxmlformats.org/drawingml/2006/main" noChangeAspect="1"/></wp:cNvGraphicFramePr><a:graphic xmlns:a="http://schemas.openxmlformats.org/drawingml/2006/main"><a:graphicData uri="http://schemas.openxmlformats.org/drawingml/2006/picture"><pic:pic xmlns:pic="http://schemas.openxmlformats.org/drawingml/2006/picture"><pic:nvPicPr><pic:cNvPr id="0" name="Picture 3"/><pic:cNvPicPr><a:picLocks noChangeAspect="1" noChangeArrowheads="1"/></pic:cNvPicPr></pic:nvPicPr><pic:blipFill><a:blip r:embed="rId6"><a:extLst><a:ext uri="{28A0092B-C50C-407E-A947-70E740481C1C}"><a14:useLocalDpi xmlns:a14="http://schemas.microsoft.com/office/drawing/2010/main" val="0"/></a:ext></a:extLst></a:blip><a:srcRect/><a:stretch><a:fillRect/></a:stretch></pic:blipFill><pic:spPr bwMode="auto"><a:xfrm flipH="1"><a:off x="0" y="0"/><a:ext cx="833755" cy="4335771"/></a:xfrm><a:prstGeom prst="rect"><a:avLst/></a:prstGeom><a:noFill/><a:ln><a:noFill/></a:ln></pic:spPr></pic:pic></a:graphicData></a:graphic><wp14:sizeRelH relativeFrom="margin"><wp14:pctWidth>0</wp14:pctWidth></wp14:sizeRelH><wp14:sizeRelV relativeFrom="margin"><wp14:pctHeight>0</wp14:pctHeight></wp14:sizeRelV></wp:anchor></w:drawing></w:r><w:r w:rsidR="00A402AC" w:rsidRPr="00FA2309"><w:rPr><w:rFonts w:asciiTheme="minorHAnsi" w:hAnsiTheme="minorHAnsi" w:cstheme="minorHAnsi"/><w:b/><w:bCs/><w:noProof/><w:color w:val="102744"/></w:rPr><w:drawing><wp:anchor distT="0" distB="0" distL="114300" distR="114300" simplePos="0" relativeHeight="251655168" behindDoc="1" locked="0" layoutInCell="1" allowOverlap="1" wp14:anchorId="466CFAE1" wp14:editId="481FD65A"><wp:simplePos x="0" y="0"/><wp:positionH relativeFrom="column"><wp:posOffset>759041</wp:posOffset></wp:positionH><wp:positionV relativeFrom="paragraph"><wp:posOffset>154507</wp:posOffset></wp:positionV><wp:extent cx="186055" cy="186055"/><wp:effectExtent l="0" t="0" r="4445" b="4445"/><wp:wrapTight wrapText="bothSides"><wp:wrapPolygon edited="0"><wp:start x="4423" y="0"/><wp:lineTo x="0" y="4423"/><wp:lineTo x="0" y="19904"/><wp:lineTo x="19904" y="19904"/><wp:lineTo x="19904" y="6635"/><wp:lineTo x="15481" y="0"/><wp:lineTo x="4423" y="0"/></wp:wrapPolygon></wp:wrapTight><wp:docPr id="2123433293" name="Graphic 18" descr="Email with solid fill"/><wp:cNvGraphicFramePr><a:graphicFrameLocks xmlns:a="http://schemas.openxmlformats.org/drawingml/2006/main" noChangeAspect="1"/></wp:cNvGraphicFramePr><a:graphic xmlns:a="http://schemas.openxmlformats.org/drawingml/2006/main"><a:graphicData uri="http://schemas.openxmlformats.org/drawingml/2006/picture"><pic:pic xmlns:pic="http://schemas.openxmlformats.org/drawingml/2006/picture"><pic:nvPicPr><pic:cNvPr id="2123433293" name="Graphic 2123433293" descr="Email with solid fill"/><pic:cNvPicPr/></pic:nvPicPr><pic:blipFill><a:blip r:embed="rId7"><a:extLst><a:ext uri="{96DAC541-7B7A-43D3-8B79-37D633B846F1}"><asvg:svgBlip xmlns:asvg="http://schemas.microsoft.com/office/drawing/2016/SVG/main" r:embed="rId8"/></a:ext></a:extLst></a:blip><a:stretch><a:fillRect/></a:stretch></pic:blipFill><pic:spPr><a:xfrm><a:off x="0" y="0"/><a:ext cx="186055" cy="186055"/></a:xfrm><a:prstGeom prst="rect"><a:avLst/></a:prstGeom></pic:spPr></pic:pic></a:graphicData></a:graphic><wp14:sizeRelH relativeFrom="margin"><wp14:pctWidth>0</wp14:pctWidth></wp14:sizeRelH><wp14:sizeRelV relativeFrom="margin"><wp14:pctHeight>0</wp14:pctHeight></wp14:sizeRelV></wp:anchor></w:drawing></w:r><w:r w:rsidR="00BE04BE" w:rsidRPr="00BE04BE"><w:rPr><w:rFonts w:asciiTheme="minorHAnsi" w:hAnsiTheme="minorHAnsi" w:cstheme="minorHAnsi"/><w:b/><w:bCs/><w:noProof/></w:rPr><w:t>support@princetonprofessional.co</w:t></w:r><w:r w:rsidR="00BE04BE"><w:rPr><w:rFonts w:asciiTheme="minorHAnsi" w:hAnsiTheme="minorHAnsi" w:cstheme="minorHAnsi"/><w:b/><w:bCs/><w:noProof/></w:rPr><w:t>m</w:t></w:r></w:p><w:p w14:paraId="2B54DDC8" w14:textId="2606E1B0" w:rsidR="00A81EB3" w:rsidRDefault="0037410B" w:rsidP="00A81EB3"><w:pPr><w:pStyle w:val="BodyText"/><w:spacing w:before="226"/><w:jc w:val="both"/><w:rPr><w:rFonts w:ascii="Calibri" w:hAnsi="Calibri" w:cs="Calibri"/><w:b/><w:bCs/></w:rPr></w:pPr><w:r w:rsidRPr="00806D19"><w:rPr><w:rFonts w:ascii="Georgia" w:hAnsi="Georgia"/><w:noProof/></w:rPr><w:drawing><wp:anchor distT="0" distB="0" distL="114300" distR="114300" simplePos="0" relativeHeight="251656192" behindDoc="1" locked="0" layoutInCell="1" allowOverlap="1" wp14:anchorId="4B97E71E" wp14:editId="19138597"><wp:simplePos x="0" y="0"/><wp:positionH relativeFrom="column"><wp:posOffset>19050</wp:posOffset></wp:positionH><wp:positionV relativeFrom="paragraph"><wp:posOffset>9525</wp:posOffset></wp:positionV><wp:extent cx="737870" cy="4247515"/><wp:effectExtent l="0" t="0" r="5080" b="635"/><wp:wrapNone/><wp:docPr id="2110047577" name="Picture 12"/><wp:cNvGraphicFramePr><a:graphicFrameLocks xmlns:a="http://schemas.openxmlformats.org/drawingml/2006/main" noChangeAspect="1"/></wp:cNvGraphicFramePr><a:graphic xmlns:a="http://schemas.openxmlformats.org/drawingml/2006/main"><a:graphicData uri="http://schemas.openxmlformats.org/drawingml/2006/picture"><pic:pic xmlns:pic="http://schemas.openxmlformats.org/drawingml/2006/picture"><pic:nvPicPr><pic:cNvPr id="0" name="Picture 3"/><pic:cNvPicPr><a:picLocks noChangeAspect="1" noChangeArrowheads="1"/></pic:cNvPicPr></pic:nvPicPr><pic:blipFill><a:blip r:embed="rId6"><a:extLst><a:ext uri="{28A0092B-C50C-407E-A947-70E740481C1C}"><a14:useLocalDpi xmlns:a14="http://schemas.microsoft.com/office/drawing/2010/main" val="0"/></a:ext></a:extLst></a:blip><a:srcRect/><a:stretch><a:fillRect/></a:stretch></pic:blipFill><pic:spPr bwMode="auto"><a:xfrm><a:off x="0" y="0"/><a:ext cx="737870" cy="4247515"/></a:xfrm><a:prstGeom prst="rect"><a:avLst/></a:prstGeom><a:noFill/><a:ln><a:noFill/></a:ln></pic:spPr></pic:pic></a:graphicData></a:graphic><wp14:sizeRelH relativeFrom="margin"><wp14:pctWidth>0</wp14:pctWidth></wp14:sizeRelH><wp14:sizeRelV relativeFrom="margin"><wp14:pctHeight>0</wp14:pctHeight></wp14:sizeRelV></wp:anchor></w:drawing></w:r><w:r w:rsidR="00A402AC"><w:rPr><w:rFonts w:ascii="Calibri" w:hAnsi="Calibri" w:cs="Calibri"/><w:b/><w:bCs/><w:noProof/></w:rPr><w:drawing><wp:anchor distT="0" distB="0" distL="114300" distR="114300" simplePos="0" relativeHeight="251661312" behindDoc="1" locked="0" layoutInCell="1" allowOverlap="1" wp14:anchorId="7A0812B1" wp14:editId="6C729955"><wp:simplePos x="0" y="0"/><wp:positionH relativeFrom="column"><wp:posOffset>732155</wp:posOffset></wp:positionH><wp:positionV relativeFrom="paragraph"><wp:posOffset>123825</wp:posOffset></wp:positionV><wp:extent cx="189865" cy="189865"/><wp:effectExtent l="0" t="0" r="0" b="635"/><wp:wrapSquare wrapText="bothSides"/><wp:docPr id="925282206" name="Graphic 21" descr="Marker with solid fill"/><wp:cNvGraphicFramePr><a:graphicFrameLocks xmlns:a="http://schemas.openxmlformats.org/drawingml/2006/main" noChangeAspect="1"/></wp:cNvGraphicFramePr><a:graphic xmlns:a="http://schemas.openxmlformats.org/drawingml/2006/main"><a:graphicData uri="http://schemas.openxmlformats.org/drawingml/2006/picture"><pic:pic xmlns:pic="http://schemas.openxmlformats.org/drawingml/2006/picture"><pic:nvPicPr><pic:cNvPr id="925282206" name="Graphic 925282206" descr="Marker with solid fill"/><pic:cNvPicPr/></pic:nvPicPr><pic:blipFill><a:blip r:embed="rId9"><a:extLst><a:ext uri="{96DAC541-7B7A-43D3-8B79-37D633B846F1}"><asvg:svgBlip xmlns:asvg="http://schemas.microsoft.com/office/drawing/2016/SVG/main" r:embed="rId10"/></a:ext></a:extLst></a:blip><a:stretch><a:fillRect/></a:stretch></pic:blipFill><pic:spPr><a:xfrm><a:off x="0" y="0"/><a:ext cx="189865" cy="189865"/></a:xfrm><a:prstGeom prst="rect"><a:avLst/></a:prstGeom></pic:spPr></pic:pic></a:graphicData></a:graphic></wp:anchor></w:drawing></w:r><w:r w:rsidR="00A402AC"><w:rPr><w:rFonts w:ascii="Calibri" w:hAnsi="Calibri" w:cs="Calibri"/><w:b/><w:bCs/></w:rPr><w:t xml:space="preserve">               </w:t></w:r><w:r w:rsidR="00A81EB3" w:rsidRPr="00A81EB3"><w:rPr><w:rFonts w:ascii="Calibri" w:hAnsi="Calibri" w:cs="Calibri"/><w:b/><w:bCs/></w:rPr><w:t xml:space="preserve">1203, Mondeal Heights, Sarkhej Gandhinagar Service </w:t></w:r></w:p><w:p w14:paraId="366DB715" w14:textId="5CC57AE2" w:rsidR="00A81EB3" w:rsidRDefault="00BE04BE" w:rsidP="00A81EB3"><w:pPr><w:pStyle w:val="BodyText"/><w:spacing w:before="226"/><w:ind w:left="1440"/><w:jc w:val="both"/><w:rPr><w:rFonts w:ascii="Calibri" w:hAnsi="Calibri" w:cs="Calibri"/><w:b/><w:bCs/></w:rPr></w:pPr><w:r w:rsidRPr="00806D19"><w:rPr><w:rFonts w:ascii="Georgia" w:hAnsi="Georgia"/><w:noProof/></w:rPr><mc:AlternateContent><mc:Choice Requires="wps"><w:drawing><wp:anchor distT="0" distB="0" distL="0" distR="0" simplePos="0" relativeHeight="251664384" behindDoc="0" locked="0" layoutInCell="1" allowOverlap="1" wp14:anchorId="748BD791" wp14:editId="5D739E4D"><wp:simplePos x="0" y="0"/><wp:positionH relativeFrom="page"><wp:posOffset>4348716</wp:posOffset></wp:positionH><wp:positionV relativeFrom="paragraph"><wp:posOffset>17956</wp:posOffset></wp:positionV><wp:extent cx="2628900" cy="935665"/><wp:effectExtent l="0" t="0" r="0" b="0"/><wp:wrapNone/><wp:docPr id="1251689391" name="Textbox 12"/><wp:cNvGraphicFramePr><a:graphicFrameLocks xmlns:a="http://schemas.openxmlformats.org/drawingml/2006/main"/></wp:cNvGraphicFramePr><a:graphic xmlns:a="http://schemas.openxmlformats.org/drawingml/2006/main"><a:graphicData uri="http://schemas.microsoft.com/office/word/2010/wordprocessingShape"><wps:wsp><wps:cNvSpPr txBox="1"><a:spLocks/></wps:cNvSpPr><wps:spPr><a:xfrm><a:off x="0" y="0"/><a:ext cx="2628900" cy="935665"/></a:xfrm><a:prstGeom prst="rect"><a:avLst/></a:prstGeom><a:solidFill><a:schemeClr val="tx2"><a:lumMod val="50000"/></a:schemeClr></a:solidFill></wps:spPr><wps:txbx><w:txbxContent><w:p w14:paraId="3B1D377D" w14:textId="77777777" w:rsidR="00BE04BE" w:rsidRDefault="00BE04BE" w:rsidP="00BE04BE"><w:pPr><w:jc w:val="both"/></w:pPr><w:r><w:t xml:space="preserve"> </w:t></w:r></w:p><w:p w14:paraId="65F54F0E" w14:textId="4A4B146F" w:rsidR="00BE04BE" w:rsidRPr="00BE04BE" w:rsidRDefault="00BE04BE" w:rsidP="00BE04BE"><w:pPr><w:jc w:val="center"/><w:rPr><w:color w:val="FFFFFF" w:themeColor="background1"/></w:rPr></w:pPr><w:r w:rsidRPr="00BE04BE"><w:rPr><w:color w:val="FFFFFF" w:themeColor="background1"/></w:rPr><w:t xml:space="preserve">TOTAL:  </w:t></w:r><w:r w:rsidRPr="00BE04BE"><w:rPr><w:color w:val="FFFFFF" w:themeColor="background1"/></w:rPr><w:tab/></w:r><w:r w:rsidRPr="00BE04BE"><w:rPr><w:color w:val="FFFFFF" w:themeColor="background1"/></w:rPr><w:tab/><w:t xml:space="preserve"> 7,000.00</w:t></w:r></w:p><w:p w14:paraId="0EE6B1FE" w14:textId="62B568BE" w:rsidR="00BE04BE" w:rsidRPr="00BE04BE" w:rsidRDefault="00BE04BE" w:rsidP="00BE04BE"><w:pPr><w:jc w:val="center"/><w:rPr><w:color w:val="FFFFFF" w:themeColor="background1"/></w:rPr></w:pPr><w:r><w:rPr><w:color w:val="FFFFFF" w:themeColor="background1"/></w:rPr><w:t xml:space="preserve"> </w:t></w:r><w:r w:rsidRPr="00BE04BE"><w:rPr><w:color w:val="FFFFFF" w:themeColor="background1"/></w:rPr><w:t>DISCOUNT:</w:t></w:r><w:r w:rsidRPr="00BE04BE"><w:rPr><w:color w:val="FFFFFF" w:themeColor="background1"/></w:rPr><w:tab/></w:r><w:r w:rsidRPr="00BE04BE"><w:rPr><w:color w:val="FFFFFF" w:themeColor="background1"/></w:rPr><w:tab/><w:t xml:space="preserve">  0,000.00</w:t></w:r></w:p><w:p w14:paraId="434711F3" w14:textId="2AADA591" w:rsidR="00BE04BE" w:rsidRPr="00BE04BE" w:rsidRDefault="00BE04BE" w:rsidP="00BE04BE"><w:pPr><w:jc w:val="center"/><w:rPr><w:color w:val="FFFFFF" w:themeColor="background1"/></w:rPr></w:pPr><w:r w:rsidRPr="00BE04BE"><w:rPr><w:color w:val="FFFFFF" w:themeColor="background1"/></w:rPr><w:t>PAID:</w:t></w:r><w:r w:rsidRPr="00BE04BE"><w:rPr><w:color w:val="FFFFFF" w:themeColor="background1"/></w:rPr><w:tab/></w:r><w:r><w:rPr><w:color w:val="FFFFFF" w:themeColor="background1"/></w:rPr><w:t xml:space="preserve">           </w:t></w:r><w:r w:rsidRPr="00BE04BE"><w:rPr><w:color w:val="FFFFFF" w:themeColor="background1"/></w:rPr><w:tab/><w:t xml:space="preserve"> 7,000.00</w:t></w:r></w:p><w:p w14:paraId="1888655B" w14:textId="21C9FF81" w:rsidR="00BE04BE" w:rsidRPr="00BE04BE" w:rsidRDefault="00BE04BE" w:rsidP="00BE04BE"><w:pPr><w:jc w:val="center"/><w:rPr><w:color w:val="FFFFFF" w:themeColor="background1"/></w:rPr></w:pPr><w:r><w:rPr><w:color w:val="FFFFFF" w:themeColor="background1"/></w:rPr><w:t xml:space="preserve"> </w:t></w:r><w:r w:rsidRPr="00BE04BE"><w:rPr><w:color w:val="FFFFFF" w:themeColor="background1"/></w:rPr><w:t>DUE:                      0,000.00</w:t></w:r></w:p><w:p w14:paraId="1468EC41" w14:textId="43A511E0" w:rsidR="00BE04BE" w:rsidRDefault="00BE04BE" w:rsidP="00BE04BE"><w:pPr><w:pStyle w:val="BodyText"/><w:spacing w:before="160" w:line="276" w:lineRule="auto"/><w:jc w:val="both"/></w:pPr></w:p></w:txbxContent></wps:txbx><wps:bodyPr wrap="square" lIns="0" tIns="0" rIns="0" bIns="0" rtlCol="0" anchor="ctr"><a:noAutofit/></wps:bodyPr></wps:wsp></a:graphicData></a:graphic><wp14:sizeRelH relativeFrom="margin"><wp14:pctWidth>0</wp14:pctWidth></wp14:sizeRelH><wp14:sizeRelV relativeFrom="margin"><wp14:pctHeight>0</wp14:pctHeight></wp14:sizeRelV></wp:anchor></w:drawing></mc:Choice><mc:Fallback><w:pict><v:shape w14:anchorId="748BD791" id="_x0000_s1029" type="#_x0000_t202" style="position:absolute;left:0;text-align:left;margin-left:342.4pt;margin-top:1.4pt;width:207pt;height:73.65pt;z-index:251664384;visibility:visible;mso-wrap-style:square;mso-width-percent:0;mso-height-percent:0;mso-wrap-distance-left:0;mso-wrap-distance-top:0;mso-wrap-distance-right:0;mso-wrap-distance-bottom:0;mso-position-horizontal:absolute;mso-position-horizontal-relative:page;mso-position-vertical:absolute;mso-position-vertical-relative:text;mso-width-percent:0;mso-height-percent:0;mso-width-relative:margin;mso-height-relative:margin;v-text-anchor:middle" o:gfxdata="UEsDBBQABgAIAAAAIQC2gziS/gAAAOEBAAATAAAAW0NvbnRlbnRfVHlwZXNdLnhtbJSRQU7DMBBF&#xA;90jcwfIWJU67QAgl6YK0S0CoHGBkTxKLZGx5TGhvj5O2G0SRWNoz/78nu9wcxkFMGNg6quQqL6RA&#xA;0s5Y6ir5vt9lD1JwBDIwOMJKHpHlpr69KfdHjyxSmriSfYz+USnWPY7AufNIadK6MEJMx9ApD/oD&#xA;OlTrorhX2lFEilmcO2RdNtjC5xDF9pCuTyYBB5bi6bQ4syoJ3g9WQ0ymaiLzg5KdCXlKLjvcW893&#xA;SUOqXwnz5DrgnHtJTxOsQfEKIT7DmDSUCaxw7Rqn8787ZsmRM9e2VmPeBN4uqYvTtW7jvijg9N/y&#xA;JsXecLq0q+WD6m8AAAD//wMAUEsDBBQABgAIAAAAIQA4/SH/1gAAAJQBAAALAAAAX3JlbHMvLnJl&#xA;bHOkkMFqwzAMhu+DvYPRfXGawxijTi+j0GvpHsDYimMaW0Yy2fr2M4PBMnrbUb/Q94l/f/hMi1qR&#xA;JVI2sOt6UJgd+ZiDgffL8ekFlFSbvV0oo4EbChzGx4f9GRdb25HMsYhqlCwG5lrLq9biZkxWOiqY&#xA;22YiTra2kYMu1l1tQD30/bPm3wwYN0x18gb45AdQl1tp5j/sFB2T0FQ7R0nTNEV3j6o9feQzro1i&#xA;OWA14Fm+Q8a1a8+Bvu/d/dMb2JY5uiPbhG/ktn4cqGU/er3pcvwCAAD//wMAUEsDBBQABgAIAAAA&#xA;IQASc4xxywEAAIYDAAAOAAAAZHJzL2Uyb0RvYy54bWysU8tu2zAQvBfoPxC811IU2EgEy0GbIEWB&#xA;9AGk+QCaIi2iFJfl0pb8911Ssh20t6A+0MvlvmZ2tL4be8sOKqAB1/CrRcmZchJa43YNf/n5+OGG&#xA;M4zCtcKCUw0/KuR3m/fv1oOvVQUd2FYFRkUc1oNveBejr4sCZad6gQvwytGjhtCLSNewK9ogBqre&#xA;26Iqy1UxQGh9AKkQyfswPfJNrq+1kvG71qgisw2n2WI+Qz636Sw2a1HvgvCdkfMY4g1T9MI4anou&#xA;9SCiYPtg/inVGxkAQceFhL4ArY1UGQOhuSr/QvPcCa8yFiIH/Zkm/H9l5bfDs/8RWBw/wUgLzCDQ&#xA;P4H8hcRNMXis55jEKdZI0QnoqEOf/gkCo0Ti9njmU42RSXJWq+rmtqQnSW+318vVapkILy7ZPmD8&#xA;rKBnyWh4oH3lCcThCeMUegpJzRCsaR+NtfmSNKLubWAHQduNY5VT7b7/Cu3kW5b0m1tmSaXwPMCr&#xA;ShnjBCsBjON2ZKZt+HVKTJ4ttEeiaCCVNBx/70VQnNkvjtaQJHUywsnYnowQ7T1MwhNOdkC6kzHk&#xA;KR183EfQJoO8NJkZp2XnKWdhJjW9vueoy+ez+QMAAP//AwBQSwMEFAAGAAgAAAAhAMy1zeXgAAAA&#xA;CgEAAA8AAABkcnMvZG93bnJldi54bWxMj0FPwzAMhe9I/IfISNxY0rFNbWk6wSQmcUCIbQeOWWPa&#xA;isYpTdaVf493gpOf9azn7xXryXVixCG0njQkMwUCqfK2pVrDYf98l4II0ZA1nSfU8IMB1uX1VWFy&#xA;68/0juMu1oJDKORGQxNjn0sZqgadCTPfI7H36QdnIq9DLe1gzhzuOjlXaiWdaYk/NKbHTYPV1+7k&#xA;NDy9yeFjeUiy/bh5/d4uXrLtfbRa395Mjw8gIk7x7xgu+IwOJTMd/YlsEJ2GVbpg9KhhzuPiqyxl&#xA;dWS1VAnIspD/K5S/AAAA//8DAFBLAQItABQABgAIAAAAIQC2gziS/gAAAOEBAAATAAAAAAAAAAAA&#xA;AAAAAAAAAABbQ29udGVudF9UeXBlc10ueG1sUEsBAi0AFAAGAAgAAAAhADj9If/WAAAAlAEAAAsA&#xA;AAAAAAAAAAAAAAAALwEAAF9yZWxzLy5yZWxzUEsBAi0AFAAGAAgAAAAhABJzjHHLAQAAhgMAAA4A&#xA;AAAAAAAAAAAAAAAALgIAAGRycy9lMm9Eb2MueG1sUEsBAi0AFAAGAAgAAAAhAMy1zeXgAAAACgEA&#xA;AA8AAAAAAAAAAAAAAAAAJQQAAGRycy9kb3ducmV2LnhtbFBLBQYAAAAABAAEAPMAAAAyBQAAAAA=&#xA;" fillcolor="#0f243e [1615]" stroked="f"><v:textbox inset="0,0,0,0"><w:txbxContent><w:p w14:paraId="3B1D377D" w14:textId="77777777" w:rsidR="00BE04BE" w:rsidRDefault="00BE04BE" w:rsidP="00BE04BE"><w:pPr><w:jc w:val="both"/></w:pPr><w:r><w:t xml:space="preserve"> </w:t></w:r></w:p><w:p w14:paraId="65F54F0E" w14:textId="4A4B146F" w:rsidR="00BE04BE" w:rsidRPr="00BE04BE" w:rsidRDefault="00BE04BE" w:rsidP="00BE04BE"><w:pPr><w:jc w:val="center"/><w:rPr><w:color w:val="FFFFFF" w:themeColor="background1"/></w:rPr></w:pPr><w:r w:rsidRPr="00BE04BE"><w:rPr><w:color w:val="FFFFFF" w:themeColor="background1"/></w:rPr><w:t xml:space="preserve">TOTAL:  </w:t></w:r><w:r w:rsidRPr="00BE04BE"><w:rPr><w:color w:val="FFFFFF" w:themeColor="background1"/></w:rPr><w:tab/></w:r><w:r w:rsidRPr="00BE04BE"><w:rPr><w:color w:val="FFFFFF" w:themeColor="background1"/></w:rPr><w:tab/><w:t xml:space="preserve"> 7,000.00</w:t></w:r></w:p><w:p w14:paraId="0EE6B1FE" w14:textId="62B568BE" w:rsidR="00BE04BE" w:rsidRPr="00BE04BE" w:rsidRDefault="00BE04BE" w:rsidP="00BE04BE"><w:pPr><w:jc w:val="center"/><w:rPr><w:color w:val="FFFFFF" w:themeColor="background1"/></w:rPr></w:pPr><w:r><w:rPr><w:color w:val="FFFFFF" w:themeColor="background1"/></w:rPr><w:t xml:space="preserve"> </w:t></w:r><w:r w:rsidRPr="00BE04BE"><w:rPr><w:color w:val="FFFFFF" w:themeColor="background1"/></w:rPr><w:t>DISCOUNT:</w:t></w:r><w:r w:rsidRPr="00BE04BE"><w:rPr><w:color w:val="FFFFFF" w:themeColor="background1"/></w:rPr><w:tab/></w:r><w:r w:rsidRPr="00BE04BE"><w:rPr><w:color w:val="FFFFFF" w:themeColor="background1"/></w:rPr><w:tab/><w:t xml:space="preserve">  0,000.00</w:t></w:r></w:p><w:p w14:paraId="434711F3" w14:textId="2AADA591" w:rsidR="00BE04BE" w:rsidRPr="00BE04BE" w:rsidRDefault="00BE04BE" w:rsidP="00BE04BE"><w:pPr><w:jc w:val="center"/><w:rPr><w:color w:val="FFFFFF" w:themeColor="background1"/></w:rPr></w:pPr><w:r w:rsidRPr="00BE04BE"><w:rPr><w:color w:val="FFFFFF" w:themeColor="background1"/></w:rPr><w:t>PAID:</w:t></w:r><w:r w:rsidRPr="00BE04BE"><w:rPr><w:color w:val="FFFFFF" w:themeColor="background1"/></w:rPr><w:tab/></w:r><w:r><w:rPr><w:color w:val="FFFFFF" w:themeColor="background1"/></w:rPr><w:t xml:space="preserve">           </w:t></w:r><w:r w:rsidRPr="00BE04BE"><w:rPr><w:color w:val="FFFFFF" w:themeColor="background1"/></w:rPr><w:tab/><w:t xml:space="preserve"> 7,000.00</w:t></w:r></w:p><w:p w14:paraId="1888655B" w14:textId="21C9FF81" w:rsidR="00BE04BE" w:rsidRPr="00BE04BE" w:rsidRDefault="00BE04BE" w:rsidP="00BE04BE"><w:pPr><w:jc w:val="center"/><w:rPr><w:color w:val="FFFFFF" w:themeColor="background1"/></w:rPr></w:pPr><w:r><w:rPr><w:color w:val="FFFFFF" w:themeColor="background1"/></w:rPr><w:t xml:space="preserve"> </w:t></w:r><w:r w:rsidRPr="00BE04BE"><w:rPr><w:color w:val="FFFFFF" w:themeColor="background1"/></w:rPr><w:t>DUE:                      0,000.00</w:t></w:r></w:p><w:p w14:paraId="1468EC41" w14:textId="43A511E0" w:rsidR="00BE04BE" w:rsidRDefault="00BE04BE" w:rsidP="00BE04BE"><w:pPr><w:pStyle w:val="BodyText"/><w:spacing w:before="160" w:line="276" w:lineRule="auto"/><w:jc w:val="both"/></w:pPr></w:p></w:txbxContent></v:textbox><w10:wrap anchorx="page"/></v:shape></w:pict></mc:Fallback></mc:AlternateContent></w:r><w:r w:rsidR="00A81EB3"><w:rPr><w:rFonts w:ascii="Calibri" w:hAnsi="Calibri" w:cs="Calibri"/><w:b/><w:bCs/></w:rPr><w:t xml:space="preserve">    </w:t></w:r><w:r w:rsidR="00A81EB3" w:rsidRPr="00A81EB3"><w:rPr><w:rFonts w:ascii="Calibri" w:hAnsi="Calibri" w:cs="Calibri"/><w:b/><w:bCs/></w:rPr><w:t xml:space="preserve">Road Near Wide Angle Cinema Ramdevnagar, Satellite, </w:t></w:r></w:p><w:p w14:paraId="446C03B5" w14:textId="3DFDF546" w:rsidR="00AD3C9A" w:rsidRPr="00285745" w:rsidRDefault="00A81EB3" w:rsidP="00A81EB3"><w:pPr><w:pStyle w:val="BodyText"/><w:spacing w:before="226"/><w:ind w:left="720" w:firstLine="720"/><w:jc w:val="both"/><w:rPr><w:rFonts w:ascii="Calibri" w:hAnsi="Calibri" w:cs="Calibri"/><w:b/><w:bCs/></w:rPr></w:pPr><w:r><w:rPr><w:rFonts w:ascii="Calibri" w:hAnsi="Calibri" w:cs="Calibri"/><w:b/><w:bCs/></w:rPr><w:t xml:space="preserve">   </w:t></w:r><w:r w:rsidRPr="00A81EB3"><w:rPr><w:rFonts w:ascii="Calibri" w:hAnsi="Calibri" w:cs="Calibri"/><w:b/><w:bCs/></w:rPr><w:t>Ahmedabad, Gujarat 380015 keep</w:t></w:r><w:r w:rsidR="00A402AC"><w:rPr><w:rFonts w:ascii="Calibri" w:hAnsi="Calibri" w:cs="Calibri"/><w:b/><w:bCs/></w:rPr><w:t xml:space="preserve"> </w:t></w:r></w:p><w:sectPr w:rsidR="00AD3C9A" w:rsidRPr="00285745" w:rsidSect="0037410B"><w:type w:val="continuous"/><w:pgSz w:w="11910" w:h="16850"/><w:pgMar w:top="0" w:right="0" w:bottom="1276" w:left="0" w:header="720" w:footer="720" w:gutter="0"/><w:cols w:space="720"/></w:sectPr></w:body></w:document>